Workbook

Sheet Pipeline Fixes
A1: WASEL — REVISED MODEL PIPELINE
A2: 9 Structured fixes addressing adversarial analysis | All figures JOD unless noted
A4: # | B4: Fix Applied | C4: Before | D4: After (Revised) | E4: Year 1 Net Impact
A5: 1 | B5: Bank Guarantee (LTRC confirmed JD 25K, not JD 50K) | C5: JD 50,000 locked | D5: JD 25,000 locked | E5: +JD 25,000 freed capital
A6: 2 | B6: Starter Tier trip soft-cap raised 6→8 trips/day | C6: Driver net: JD 20/mo | D6: Driver net: JD 123/mo | E6: Viability restored; churn ↓
A7: 3 | B7: Fare adjusted to JD 2.37 (5% below Uber/Careem) | C7: JD 2.50/trip | D7: JD 2.37/trip | E7: Rider acquisition ↑; driver GMV maintained via higher trip cap
A8: 4 | B8: Rider marketing — phased spend (see Rider Economics sheet) | C8: JD 3,000/mo flat | D8: JD 12K / 8K / 5K by phase | E8: −JD 54,000 additional spend
A9: 5 | B9: Rider subscription revenue (NEW: Wasel Go + Wasel Pass) | C9: JD 0 | D9: ~JD 130K Year 1 | E9: +JD 130K new revenue
A10: 6 | B10: Boycott tailwind — 1.25× rider acquisition efficiency | C10: Not modelled | D10: Modelled explicitly | E10: Same spend → 25% more riders
A11: 7 | B11: OPEX variance decomposed (JD 404K → real line items) | C11: Single opaque line | D11: 8 explicit buckets + Y2 tail | E11: Investor credibility ↑
A12: 8 | B12: Driver growth rate revised to 28% MoM (was 30%) | C12: 30% MoM assumed, unvalidated | D12: 28% MoM demand-justified | E12: Model defensibility ↑
A13: 9 | B13: Rider Economics sheet added (full 12-month demand model) | C13: Not modelled | D13: Full 12-month rider model | E13: 2nd revenue pillar in Y1
A15: YEAR 1 P&L DELTA — BASE vs. REVISED MODEL
A16: Line Item | C16: Base Model (JOD) | D16: Revised Model (JOD) | E16: Delta
A17: Driver Subscription Revenue | C17: 157261 | D17: 157261 | E17: 0
A18: Rider Subscription Revenue (NEW) | C18: 0 | D18: 130000 | E18: +JD 130,000
A19: Total Revenue | C19: 157261 | D19: 287261 | E19: +JD 130,000
A20: Cost of Revenue | C20: -139169 | D20: -139169 | E20: Unchanged
A21: Gross Profit | C21: 18092 | D21: 148092 | E21: +JD 130,000
A22: Gross Margin % | C22: 11.5% | D22: 51.6% | E22: ↑ 40pp
A23: Total Operating Expenses | C23: -807760 | D23: -807760 | E23: Unchanged
A24: Additional Rider Marketing Spend | C24: 0 | D24: -54000 | E24: −JD 54,000
A25: Adjusted EBITDA | C25: -789668 | D25: -713668 | E25: +JD 76,000
A26: Net Loss (Year 1) | C26: -801334 | D26: -727334 | E26: +JD 74,000
A27: Capital Freed (bank guarantee fix) | C27: 0 | D27: 25000 | E27: +JD 25,000
A28: Effective Funding Gap (revised) | C28: -436944 | D28: -362944 | E28: +JD 74,000
A29: Recommended Raise (with 30% buffer) | C29: 568000 | D29: 472000 | E29: −JD 96,000

Sheet Rider Economics
A1: WASEL — RIDER ECONOMICS & DEMAND-SIDE MODEL
A2: Revised model integrating boycott tailwind, rider tier subscriptions, and phased marketing spend | JOD
A4: BOYCOTT TAILWIND ANALYSIS
A5: Factor | B5: Detail | C5: Evidence / Source
A6: Trigger | B6: Uber invested $30M+ in Israeli drone firm Flytrex (Sep 2025) | C6: Middle East Monitor, Business & Human Rights Resource Centre
A7: Careem exposure | B7: 100% Uber-owned — same reputational contagion applies | C7: Wikipedia / Uber newsroom
A8: Jordan sentiment | B8: Strong pro-Palestine consumer activism; prior #boycottUberandCareem campaigns | C8: Arabian Business; IAATW worker pledges
A9: Market gap | B9: Only 4 licensed operators; Uber + Careem hold 11,600 of 11,600 vehicles | C9: Jordan News, Dec 2024
A10: Acquisition multiplier | B10: 1.25× — same JOD spend captures 25% more riders vs. neutral market | C10: Conservative BDS-driven organic lift estimate
A11: Driver switching tailwind | B11: Drivers want to 'work Jordanian'; reduces effective driver CAC by 10–15% | C11: Qualitative; consistent with Careem's original Arab growth story
A13: RIDER TIER STRUCTURE (JORDAN-OPTIMISED)
A14: Tier | B14: Monthly Fee (JOD) | C14: Fare Discount | D14: Cancellations | E14: Surge Protection | F14: Break-even Rides/Mo | G14: Target Segment
A15: Standard (Free) | B15: JD 0 | C15: None | D15: 2 free | E15: No | F15: N/A | G15: Occasional, cash-preferring users
A16: Wasel Go — JD 5/mo | B16: JD 5 | C16: 10% off all rides | D16: 6 free | E16: Capped at JD 2.00 surcharge | F16: 21 rides (JD 0.237/ride savings) | G16: Regular commuters, university students, 3×/week users
A17: Wasel Pass — JD 10/mo | B17: JD 10 | C17: 18% off + 2 free rides/mo (JD 4.74 value) | D17: Unlimited | E17: No surge pricing | F17: 12 rides | G17: Daily commuters, corporate users, road-warriors
A19: MONTHLY RIDER ACQUISITION & SUBSCRIPTION REVENUE
A20: Line Item | C20: M1 | D20: M2 | E20: M3 | F20: M4 | G20: M5 | H20: M6 | I20: M7 | J20: M8 | K20: M9 | L20: M10 | M20: M11 | N20: M12 | O20: Year 1 Total
A21: New Riders Acquired (Base) | C21: 2000 | D21: 2500 | E21: 3500 | F21: 3500 | G21: 3500 | H21: 3500 | I21: 3000 | J21: 3000 | K21: 3000 | L21: 3000 | M21: 2800 | N21: 2800 | O21: 36100
A22: Boycott Efficiency Multiplier | C22: 1.29 | D22: 1.29 | E22: 1.29 | F22: 1.29 | G22: 1.29 | H22: 1.29 | I22: 1.29 | J22: 1.29 | K22: 1.29 | L22: 1.29 | M22: 1.29 | N22: 1.29 | O22: —
A23: Effective New Riders (adj.) | C23: 2500 | D23: 3125 | E23: 4375 | F23: 4375 | G23: 4375 | H23: 4375 | I23: 3750 | J23: 3750 | K23: 3750 | L23: 3750 | M23: 3500 | N23: 3500 | O23: 45125
A24: Total Active Rider Base (EoM) | C24: 2000 | D24: 4400 | E24: 7680 | F24: 10796 | G24: 13756 | H24: 16568 | I24: 18740 | J24: 20803 | K24: 22763 | L24: 24625 | M24: 26193 | N24: 27684 | O24: 196,008 cumulative
A25: — Standard (free, 85%) | C25: 1700 | D25: 3740 | E25: 6528 | F25: 9177 | G25: 11693 | H25: 14083 | I25: 15929 | J25: 17683 | K25: 19349 | L25: 20931 | M25: 22264 | N25: 23531 | O25: 166,608 cumulative
A26: — Wasel Go (paid, 10%) | C26: 200 | D26: 440 | E26: 768 | F26: 1080 | G26: 1376 | H26: 1657 | I26: 1874 | J26: 2080 | K26: 2276 | L26: 2462 | M26: 2619 | N26: 2768 | O26: 19,600 cumulative
A27: — Wasel Pass (paid, 5%) | C27: 100 | D27: 220 | E27: 384 | F27: 540 | G27: 688 | H27: 828 | I27: 937 | J27: 1040 | K27: 1138 | L27: 1231 | M27: 1310 | N27: 1384 | O27: 9,800 cumulative
A28: Rider Marketing Spend (JOD) | C28: 12000 | D28: 12000 | E28: 12000 | F28: 8000 | G28: 8000 | H28: 8000 | I28: 5000 | J28: 5000 | K28: 5000 | L28: 5000 | M28: 5000 | N28: 5000 | O28: 90000
A29: Cost per Rider — Effective (JOD) | C29: 4.8 | D29: 3.84 | E29: 2.74 | F29: 1.83 | G29: 1.83 | H29: 1.83 | I29: 1.33 | J29: 1.33 | K29: 1.33 | L29: 1.33 | M29: 1.43 | N29: 1.43 | O29: —
A30: Wasel Go Revenue (JOD) | C30: 1000 | D30: 2200 | E30: 3840 | F30: 5398 | G30: 6878 | H30: 8284 | I30: 9370 | J30: 10402 | K30: 11382 | L30: 12312 | M30: 13096 | N30: 13842 | O30: 98004
A31: Wasel Pass Revenue (JOD) | C31: 1000 | D31: 2200 | E31: 3840 | F31: 5398 | G31: 6878 | H31: 8284 | I31: 9370 | J31: 10402 | K31: 11382 | L31: 12312 | M31: 13096 | N31: 13842 | O31: 98004
A32: Total Rider Subscription Revenue | C32: 1995 | D32: 4389 | E32: 7661 | F32: 10769 | G32: 13722 | H32: 16527 | I32: 18693 | J32: 20751 | K32: 22706 | L32: 24563 | M32: 26128 | N32: 27615 | O32: 195519
A34: RIDER DEMAND vs. DRIVER CAPACITY VALIDATION
A35: Metric | C35: Month 6 | D35: Month 9 | E35: Month 12 | F35: Notes
A36: Active Riders (EoM) | C36: 16568 | D36: 22763 | E36: 27684 | F36: With 1.25× boycott multiplier applied
A37: Avg Rides per Rider per Month | C37: 8.5 | D37: 8.5 | E37: 8.5 | F37: Blended: 60% light/4 rides, 30% regular/12, 10% heavy/25
A38: Total Demand-Side Rides | C38: 140828 | D38: 193486 | E38: 235314 | F38: Rides that riders want to take
A39: Total Supply-Side Rides | C39: 119106 | D39: 203112 | E39: 346086 | F39: Driver capacity × trips/day (from Monthly P&L)
A40: Demand Coverage % | C40: 118% | D40: 95% | E40: 68% | F40: ⚠ At M12: accelerate rider acquisition to 40K to reach 100%
A42: OPEX VARIANCE DECOMPOSITION (JD 403,880 → Real Line Items)
A43: Line Item | B43: Y1 Amount (JOD) | C43: Y2 Tail (15%) | D43: Y3 Tail (5%) | E43: Type | F43: Rationale
A44: Legal / regulatory dispute reserves | B44: 50000 | C44: 7500 | D44: 2500 | E44: One-time + tail | F44: LTRC challenges, driver disputes, IP filings
A45: Technology rebuild / MVP v2 | B45: 40000 | C45: 6000 | D45: 2000 | E45: One-time + tail | F45: Post-launch rebuild from real user feedback
A46: Regulatory compliance contingency | B46: 80000 | C46: 12000 | D46: 4000 | E46: Annual + tail | F46: LTRC annual audit, data compliance, permit battles
A47: Launch friction / operational delays | B47: 50000 | C47: 7500 | D47: 2500 | E47: One-time | F47: Delayed hiring, vendor disputes, logistics slippage
A48: Additional rider marketing (reclassified) | B48: 54000 | C48: 0 | D48: 0 | E48: Reclassified | F48: Moved to Rider Economics dedicated budget line
A49: OPEX overrun buffer (sales tax, utilities, misc) | B49: 83880 | C49: 12582 | D49: 4194 | E49: Rolling | F49: Catch-all for sub-JD5K items and FX effects
A50: TOTAL OPEX VARIANCE | B50: 357880 | C50: 45582 | D50: 15194 | E50: — | F50: JD 46K recurs in Y2; JD 15K in Y3 (vs JD 0 base model)

Sheet Rider Strategy v2
A1: WASEL — RIDER STRATEGY v2.0 ECONOMIC ADJUSTMENTS
A2: All figures JOD | Structural acquisition model — boycott-independent | February 2026
A4: SECTION 1: REVISED RIDER CAC BY CHANNEL
A5: # | B5: Channel | C5: Raw CAC (JOD) | D5: Multiplier | E5: Effective CAC (JOD) | F5: Reliability
A6: 1 | B6: WASEL SAFE TRIP™ live link | C6: JD 0 | D6: 1.0× | E6: JD 0.80 | F6: Permanent
A7: 2 | B7: University connector (15 campuses) | C7: JD 0.50 | D7: 1.6× | E7: JD 1.85 | F7: Permanent
A8: 3 | B8: Subscription upgrade (internal conversion) | C8: JD 0 | D8: N/A | E8: JD 0.15 | F8: Permanent
A9: 4 | B9: Driver in-car referral | C9: JD 2.37 (1 free ride) | D9: 3.5× | E9: JD 0.68 | F9: Permanent
A10: 5 | B10: Facebook lookalike ads (waitlist only) | C10: JD 4.00 | D10: 1.29× | E10: JD 3.10 | F10: Temporary
A11: 6 | B11: Campus activation events | C11: JD 1.50 | D11: 1.8× | E11: JD 0.83 | F11: High (academic year)
A12: 7 | B12: WhatsApp organic (driver community) | C12: JD 0.20 | D12: 2.0× | E12: JD 0.10 | F12: Permanent
A13: TOTAL | B13: BLENDED EFFECTIVE CAC (REVISED) | C13: — | D13: 1.29× | E13: JD 1.42 | F13: STRUCTURAL — no boycott dependency
A15: SECTION 2: RIDER LTV BY TIER
A16: Tier | B16: Avg ARPU/Mo (JOD) | C16: Avg Lifespan (Mo) | D16: Monthly Churn | E16: LTV (JOD) | F16: LTV/CAC Ratio
A17: Standard (Free) | B17: JD 0 | C17: 4.2 | D17: 18% | E17: JD 0 | F17: N/A
A18: Wasel Go (JD 4.99/mo) | B18: JD 4.99 | C18: 11.5 | D18: 7% | E18: JD 57.38 | F18: 40.4×
A19: Wasel Pass (JD 9.99/mo) | B19: JD 9.99 | C19: 18.2 | D19: 4% | E19: JD 181.82 | F19: 128×
A20: Wasel VIP (JD 19.99/mo) | B20: JD 19.99 | C20: 28+ | D20: 2% | E20: JD 559.72 | F20: 394×
A21: Corporate (per seat) | B21: JD 14.50 | C21: 24+ | D21: 3% | E21: JD 348.00 | F21: 245×
A22: BLENDED (10%/5%/1%/5%) | B22: JD 6.80 | C22: 14.1 | D22: 6.5% | E22: JD 95.88 | F22: 67.5×
A24: SECTION 3: REVISED RIDER SUBSCRIPTION REVENUE (WITH VIP TIER)
A25: Line Item | B25: M3 | C25: M6 | D25: M9 | E25: M12 | F25: Y1 Total (JOD)
A26: Wasel Go Revenue (JD 4.99/mo) | B26: JD 3,833 | C26: JD 8,251 | D26: JD 11,362 | E26: JD 13,800 | F26: JD 97,518
A27: Wasel Pass Revenue (JD 9.99/mo) | B27: JD 3,836 | C27: JD 8,268 | D27: JD 11,371 | E27: JD 13,812 | F27: JD 97,890
A28: Wasel VIP Revenue (JD 19.99/mo, from M6) | B28: JD 0 | C28: JD 828 | D28: JD 2,275 | E28: JD 5,191 | F28: JD 10,814
A29: TOTAL Rider Subscription Revenue | B29: JD 7,669 | C29: JD 17,347 | D29: JD 25,008 | E29: JD 32,803 | F29: JD 206,222
A30: vs. Base Model delta | B30: +JD 8 | C30: +JD 820 | D30: +JD 2,302 | E30: +JD 5,188 | F30: +JD 10,703
A32: SECTION 4: 90-DAY TACTICAL GANTT (RIDER STRATEGY)
A33: Week | B33: Phase | C33: Initiative | D33: Owner | E33: Budget (JOD) | F33: Success Metric
A34: W1-2 | B34: Foundation | C34: WASEL LOCK™ — pre-booking fare guarantee live | D34: Tech | E34: Dev only | F34: 100% rides show locked fare
A35: W1-2 | B35: Foundation | C35: WASEL SAFE TRIP™ + SOS prominence built | D35: Tech | E35: Dev only | F35: Live link in <2 taps
A36: W2-3 | B36: Foundation | C36: WhatsApp CRM Day 0-7 onboarding sequence | D36: Growth | E36: JD 400/mo | F36: Message delivery >98%
A37: W3-4 | B37: Foundation | C37: Subscription paywall: Go JD 4.99 / Pass JD 9.99 / decoy | D37: Product | E37: Dev only | F37: A/B variants ready
A38: W3-4 | B38: Acquisition | C38: University connectors: 15 campuses, 30 cards each | D38: Growth | E38: JD 750 | F38: 15 connectors confirmed
A39: W4-5 | B39: Acquisition | C39: First Ride Guarantee + JD 1.00 auto-credit on driver cancel | D39: Product | E39: JD 500 reserve | F39: Guarantee tracking active
A40: W5-8 | B40: Activation | C40: Behavioral nudges: surge loss-aversion + streak mechanic | D40: Growth | E40: JD 200 CRM | F40: Subscription conversion >25%
A41: W5-8 | B41: Activation | C41: Give-not-earn referral + WhatsApp share card | D41: Growth | E41: JD 300 design | F41: K-factor >0.25
A42: W8-10 | B42: Optimization | C42: KPI dashboard: CAC/channel, LTV/tier, churn/cohort | D42: Analytics | E42: JD 600 tooling | F42: Dashboard live with M1-M2 data
A43: W10-12 | B43: Optimization | C43: Cash agent network: 10 stations + 5 pharmacies | D43: Ops | E43: JD 1,000 setup | F43: Top-up in 15 locations

Sheet Assumptions
A1: WASEL — SUBSCRIPTION-BASED RIDE-HAILING PLATFORM
A2: MASTER ASSUMPTIONS & INPUTS (REVISED)
A4: MARKET & LAUNCH PARAMETERS
A5: Metric | B5: Value | C5: Unit | D5: Source / Notes
A6: Target City | B6: Amman | C6: — | D6: Capital of Jordan; 4.5M metro population
A7: Launch Month | B7: Month 1 | C7: — | D7: Phase 1 launch target
A8: Avg Fare per Trip (JOD) | B8: 2.37 | C8: JOD | D8: Benchmark: taxi rides 2-3 JOD within Amman; similar in Irbid/Zarqa
A9: Avg Trips per Driver per Day (Blended) | B9: 9 | C9: trips | D9: Range 7-11; blended across tiers, higher for multi-city
A10: Operating Days per Month | B10: 26 | C10: days | D10: 6 days/week average
A11: Est. Monthly Gross Fare Revenue (Blended) | B11: =B8*B9*B10 -> 554.58 | C11: JOD/driver | D11: Targeting ~JD 450–650; validates driver economics
A12: Payment Mix — Cash % | B12: 0.65 | C12: % | D12: Jordan cash-heavy; <50% made digital payment in 2024
A13: Payment Mix — Digital % | B13: =1-B12 -> 0.35 | C13: % | D13: Growing: mobile wallets at 2.59M users (2024)
A14: Payment Processing Fee (Digital) | B14: 0.03 | C14: % | D14: HyperPay/MadfooatCom MENA standard: 2.5-3.5%
A15: JOD to USD Exchange Rate | B15: 1.41 | C15: USD/JOD | D15: Fixed peg: 1 JOD ≈ $1.41 USD
A17: DRIVER ECONOMICS
A18: Metric | B18: Value | C18: Unit | D18: Source / Notes
A19: Fuel Cost / Driver / Month | B19: 200 | C19: JOD | D19: ~JD 7.70/day × 26 days; Amman fuel prices
A20: Maintenance Cost / Driver / Month | B20: 120 | C20: JOD | D20: Oil, tires, brakes, general upkeep
A21: Data & Misc / Driver / Month | B21: 30 | C21: JOD | D21: Mobile data plan + misc expenses
A22: Total Driver Operating Costs | B22: =SUM(B19:B21) -> 350 | C22: JOD/mo | D22: Total monthly cost to operate as a driver
A23: Net Driver Income (Before Subscription) | B23: =B11-B22 -> 204.58 | C23: JOD/mo | D23: Gross fares minus driver operating costs
A24: Net Driver Income (After Sub, Blended) | B24: =B23-B50 -> 172.33 | C24: JOD/mo | D24: After Wasel subscription fee (blended avg)
A26: DRIVER GROWTH ASSUMPTIONS
A27: Metric | B27: Value | C27: Unit | D27: Source / Notes
A28: Starting Drivers (Month 1) | B28: 250 | C28: drivers | D28: Soft launch cohort in Amman; expanding to Irbid/Zarqa/Aqaba in Y1
A29: Monthly Driver Growth Rate | B29: 0.28 | C29: % MoM | D29: Validated with driver community; 28% MoM driven by word-of-mouth + JD 15 referral + solving real pain (28% commission)
A30: Max Drivers (Phase 1 Cap) | B30: 25000 | C30: drivers | D30: Amman capacity constraint; Phase 1 ceiling
A32: GRADUATED ONBOARDING PROGRAM
A33: Stage | B33: Duration | C33: Sub Fee (JOD) | D33: Trip Soft-Cap | E33: Churn at Transition | F33: Notes
A34: Month 0 (Trial) | B34: 1 month | C34: 0 | D34: 5 trips/day | E34: 0.3 | F34: Free trial; limited dispatches to reduce risk
A35: Month 1 (Ramp) | B35: 1 month | C35: 10 | D35: 7 trips/day | E35: 0.12 | F35: Discounted ramp; 12% drop at full-price transition
A36: Month 2+ (Active) | B36: Ongoing | C36: Auto-assign tier | D36: Per tier | E36: See below | F36: Full platform access; tier-based pricing
A38: TRANSITION-BASED CHURN
A39: Transition Point | B39: Churn Rate | C39: Notes
A40: M0 → M1 (trial to ramp) | B40: 0.25 | C40: 30% drop at first payment wall | D40: 25% drop at first payment wall (improved with JD 10 ramp pricing)
A41: M1 → M2 (ramp to full price) | B41: 0.12 | C41: 12% drop at full-price tier assignment
A42: M2–M6 (early active) | B42: 0.04 | C42: 5% monthly; still building loyalty
A43: M6+ (mature) | B43: 0.02 | C43: 2.5% monthly; strong retention
A45: TIERED SUBSCRIPTION PLAN — DRIVER FEES (3 TIERS)
A46: Tier Name | B46: Monthly Fee (JOD) | C46: Monthly Fee (USD) | D46: Driver Mix % | E46: Trips/Day (Soft-Cap) | F46: Est. Monthly Driver Revenue (JOD) | G46: Key Benefits
A47: 🟢 Starter | B47: 20 | C47: =B47*$B$15 -> 28.2 | D47: 0.45 | E47: 8 | F47: =E47*$B$8*$B$10 -> 492.96 | G47: Standard ride queue, basic app access, self-managed
A48: 🔵 Core | B48: 35 | C48: =B48*$B$15 -> 49.35 | D48: 0.35 | E48: 9 | F48: =E48*$B$8*$B$10 -> 554.58 | G48: Priority dispatch, premium rides, phone support, roadside assist
A49: 🟡 Pro | B49: 55 | C49: =B49*$B$15 -> 77.55 | D49: 0.2 | E49: 12 | F49: =E49*$B$8*$B$10 -> 739.44 | G49: Top priority, VIP rides, insurance subsidy, maintenance discounts
A50: Blended Avg Fee (JOD) | B50: =SUMPRODUCT(B47:B49,D47:D49) -> 32.25 | D50: Validation: | E50: =SUM(D47:D49) -> 1
A51: Blended Avg Fee (USD) | B51: =B50*B15 -> 45.4725
A53: INSURANCE & MAINTENANCE INCENTIVE PROGRAM
A54: Program Component | B54: Cost to Platform (JOD/driver/mo) | C54: Eligible Tiers | D54: Description
A55: Third-Party Liability (Group Policy) | B55: 5 | C55: All Tiers | D55: Platform-level group policy; JD 20K min/accident per regulation
A56: Comprehensive Top-Up Subsidy | B56: 8 | C56: Pro Only | D56: Subsidized comprehensive coverage (collision + theft); platform pays ~50%
A57: Roadside Assistance Partnership | B57: 3 | C57: Core + Pro | D57: 24/7 roadside assistance via local partner (AAJ / insurer add-on)
A58: Maintenance Discount Network | B58: 2 | C58: Pro Only | D58: 15-25% discount at partner garages; platform subsidizes booking fee
A59: Blended Insurance Cost / Driver / Mo | B59: =B55+(B56*D49)+(B57*(D48+D49))+(B58*D49) -> 8.65 | C59: JOD | D59: Weighted avg across 3-tier mix
A61: OPERATING COST ASSUMPTIONS (MONTHLY)
A62: Cost Category | B62: Monthly Cost (JOD) | C62: Type | D62: Notes
A63: Cloud Infrastructure (AWS/Firebase) | B63: 800 | C63: Semi-Fixed | D63: EC2 + RDS + S3 + Firebase + Maps API. Phase 1 baseline.
A64: Google Maps / Location API | B64: 400 | C64: Variable | D64: ~$7/1K requests. Scales with rides.
A65: SMS / Push Notification Services | B65: 200 | C65: Variable | D65: Twilio/local gateway. ~0.015 JOD per SMS × ride notifications
A66: Customer Support (Outsourced) | B66: 1500 | C66: Semi-Fixed | D66: 3-4 agents at JD 400/mo. Ticket cost ~JD 1.50
A67: Driver Onboarding & Verification | B67: 15 | C67: Per Driver | D67: Background check, doc verification, vehicle inspection
A68: Marketing & Driver Acquisition (CAC) | B68: 30 | C68: Per New Driver | D68: Referral bonus JD 18 + digital ads JD 12. Higher spend to fuel 30% MoM growth.
A69: Rider Acquisition & Promos | B69: 3000 | C69: Fixed | D69: First-ride promos, social media, influencer partnerships. Higher spend to build rider demand matching driver supply.
A71: OPEX VARIANCE BANDS
A72: Period | B72: Variance | C72: Notes
A73: Month 1 (Launch) | B73: 0.15 | C73: Baseline — no variance
A74: Months 2–4 (Early Ops) | B74: 0.07 | C74: +20% above baseline for startup friction
A75: Months 5–12 (Stabilizing) | B75: 0.1 | C75: +10% as operations mature
A77: TEAM & OVERHEAD (FIXED MONTHLY)
A78: Role / Item | B78: Headcount | C78: Monthly Cost (JOD) | D78: Notes
A79: CEO / Founder | B79: 1 | C79: 2000 | D79: Below-market startup salary
A80: CTO / Lead Engineer | B80: 1 | C80: 1800 | D80: Full-stack + mobile; equity-compensated
A81: Operations Manager | B81: 1 | C81: 1200 | D81: Driver relations, onboarding, QA
A82: Marketing / Growth Lead | B82: 1 | C82: 1000 | D82: Digital marketing, partnerships
A83: Finance / Compliance | B83: 0.5 | C83: 600 | D83: Part-time; regulatory filings, bookkeeping
A84: Office / Co-working Space | B84: — | C84: 500 | D84: Shared workspace in Amman (e.g., Zain Innovation Campus)
A85: Legal & Accounting (Retainer) | B85: — | C85: 400 | D85: Monthly retainer for legal counsel + audit prep
A86: Miscellaneous / Contingency | B86: — | C86: 500 | D86: Travel, supplies, unforeseen
A87: TOTAL TEAM & OVERHEAD | B87: =SUM(B79:B86) -> 4.5 | C87: 7500 | D87: Minimum viable team for Phase 1
A89: REGULATORY & LICENSING
A90: Item | B90: Annual Cost (JOD) | C90: Monthly Equiv. (JOD) | D90: Notes
A91: LTRC Platform License Fee | B91: 100000 | C91: =B91/12 -> 8333.3333 | D91: JD 100K/year for up to 3,000 cars. LTRC discussing reduction.
A92: Per-Vehicle Registration Fee | B92: 70 | C92: Per car/yr | D92: JD 70 per additional car above 3,000. Negligible at Phase 1.
A93: Driver Permit Fee (passed to driver) | B93: 200 | C93: Per driver/yr | D93: Drivers demand reduction from JD 400 to JD 200. Platform may subsidize.
A94: Bank Guarantee (Deposit) | B94: 25000 | C94: =B94/12 -> 2083.3333 | D94: Required deposit with LTRC. One-time but ties up capital.
A95: Company Registration & Legal Setup | B95: 5000 | C95: One-time | D95: Transport objective in articles, min share capital, legal fees.
A96: Annual Compliance & Audit | B96: 3000 | C96: =B96/12 -> 250 | D96: Annual audit, regulatory filings, data reporting to LTRC.
A98: TOTAL ANNUAL REGULATORY | B98: =B91+B94+B95+B96 -> 133000 | C98: =B98/12 -> 11083.333 | D98: Excludes one-time setup & per-driver permits
A100: PRE-LAUNCH CAPITAL REQUIRED
A101: Item | B101: Amount (JOD) | C101: Amount (USD) | D101: Notes
A102: App Development (MVP) | B102: 35000 | C102: =B102*$B$15 -> 49350 | D102: Rider app + Driver app + Admin panel. 3-4 month build.
A103: LTRC License Fee (Year 1) | B103: =B91 -> 100000 | C103: =B103*$B$15 -> 141000 | D103: Paid upfront before operations begin
A104: Bank Guarantee (Deposit) | B104: =B94 -> 25000 | C104: =B104*$B$15 -> 35250 | D104: Refundable deposit; ties up working capital
A105: Company Registration & Legal | B105: =B95 -> 5000 | C105: =B105*$B$15 -> 7050 | D105: One-time incorporation + regulatory setup
A106: Initial Marketing & Launch Campaign | B106: 10000 | C106: =B106*$B$15 -> 14100 | D106: Pre-launch brand awareness, driver recruitment blitz
A107: Working Capital Buffer (3 months OPEX) | B107: 40000 | C107: =B107*$B$15 -> 56400 | D107: Covers 3 months of operating expenses before revenue stabilizes
A109: TOTAL PRE-LAUNCH CAPITAL REQUIRED | B109: =SUM(B102:B107) -> 190000 | C109: =B109*$B$15 -> 267900 | D109: Seed round / founder capital target
D110: Total, 740,000 JOD 14 Month runway
A111: REGULATORY CAPITAL RESERVE
A112: Item | B112: Amount (JOD) | C112: Notes
A113: Locked Capital (License + Guarantee) | B113: =B91+B94 -> 125000 | C113: License fee + bank guarantee; tied up year 1
A114: Buffer (30%) | B114: =B113*0.3 -> 37500 | C114: Safety margin for unexpected regulatory costs
...

Sheet Tiered Plans
A1: TIERED SUBSCRIPTION PLANS — DETAILED BREAKDOWN
A2: Driver Subscription Tiers — Value Proposition & Feature Matrix (3 Tiers, Soft-Cap Model)
A4: PLAN OVERVIEW
A5: Feature / Metric | B5: 🟢 STARTER | C5: 🔵 CORE | D5: 🟡 PRO | E5: Notes
A6: Monthly Subscription Fee (JOD) | B6: =Assumptions!B47 -> 20 | C6: =Assumptions!B48 -> 35 | D6: =Assumptions!B49 -> 55 | E6: Driver keeps 100% of fare revenue
A7: Monthly Fee (USD Equiv.) | B7: =Assumptions!C47 -> 28.2 | C7: =Assumptions!C48 -> 49.35 | D7: =Assumptions!C49 -> 77.55 | E7: At JOD/USD peg of 1.41
A8: Target Driver Profile | B8: Part-time / new drivers | C8: Full-time daily drivers | D8: High-volume professionals | E8: Self-selection by earning level
A9: Expected Driver Mix | B9: =Assumptions!D47 -> 0.45 | C9: =Assumptions!D48 -> 0.35 | D9: =Assumptions!D49 -> 0.2 | E9: Phase 1 assumption; shifts as platform matures
A10: Trips/Day (Soft-Cap) | B10: =Assumptions!E47 -> 8 | C10: =Assumptions!E48 -> 9 | D10: =Assumptions!E49 -> 12 | E10: Priority reduction above cap, not hard block
A11: Est. Monthly Gross Fare Revenue (JOD) | B11: =Assumptions!F47 -> 492.96 | C11: =Assumptions!F48 -> 554.58 | D11: =Assumptions!F49 -> 739.44 | E11: 100% retained by driver
A12: Subscription as % of Gross Revenue | B12: =B6/B11 -> 0.040571243 | C12: =C6/C11 -> 0.063110823 | D12: =D6/D11 -> 0.074380612 | E12: vs. Uber/Careem 30% commission — massive driver savings
A14: SOFT-CAP DISPATCH MECHANICS
A15: Tier | B15: Soft-Cap (trips/day) | C15: Below Cap | D15: Above Cap | E15: Design Rationale
A16: 🟢 Starter | B16: 8 | C16: Normal dispatch priority | D16: Reduced priority; longer wait for requests | E16: Encourages upgrade to Core for high-activity drivers
A17: 🔵 Core | B17: 9 | C17: Priority dispatch | D17: Drops to standard priority | E17: Sweet spot for full-time drivers; upsell path to Pro
A18: 🟡 Pro | B18: 12 | C18: Top priority + VIP access | D18: Drops to priority (Core-level) | E18: Highest earners; rarely hit cap at 12 trips/day
A20: FEATURE MATRIX
A21: Feature | B21: 🟢 STARTER | C21: 🔵 CORE | D21: 🟡 PRO | E21: Impact
A22: DISPATCH & RIDE ACCESS
A23: Standard ride queue | B23: ✓ | C23: ✓ | D23: ✓ | E23: All tiers get ride requests
A24: Priority dispatch algorithm | B24: — | C24: ✓ | D24: ✓✓ | E24: Higher tier = first in queue for nearby rides
A25: Premium / VIP ride access | B25: — | C25: — | D25: ✓ | E25: Airport runs, corporate accounts, higher-fare rides
A26: Airport & hotel queue access | B26: — | C26: — | D26: ✓ | E26: Exclusive high-value pickup zones
A27: SUPPORT & ACCOUNT MANAGEMENT
A28: In-app chat support | B28: ✓ | C28: ✓ | D28: ✓ | E28: Standard response time
A29: Dedicated phone support line | B29: — | C29: ✓ | D29: ✓ | E29: Priority resolution for Core+
A30: INSURANCE & PROTECTION
A31: Third-party liability (platform policy) | B31: ✓ | C31: ✓ | D31: ✓ | E31: Mandatory: JD 20K min/accident (Jordan regulation)
A32: Roadside assistance (24/7) | B32: — | C32: ✓ | D32: ✓ | E32: Towing, battery, tire service via partner
A33: Comprehensive top-up insurance (50% subsidy) | B33: — | C33: — | D33: ✓ | E33: Collision + theft; platform pays half the premium
A34: MAINTENANCE & VEHICLE CARE
A35: Partner garage network (15-25% discount) | B35: — | C35: — | D35: ✓ | E35: Oil change, brakes, tires at negotiated rates
A36: Free annual vehicle inspection | B36: — | C36: — | D36: ✓ | E36: Compliance + safety check at no cost
A39: INSURANCE PROGRAM — DETAILED STRUCTURE
A40: Coverage Type | B40: Coverage Amount | C40: Platform Cost / Driver / Mo | D40: Driver Pays | E40: Eligible Tiers
A41: Mandatory Third-Party Liability | B41: JD 20,000 min per accident | C41: JD 5.00 | D41: JD 0 (included) | E41: All Tiers
A42: Comprehensive Vehicle (Top-Up) | B42: Collision, theft, fire, natural disaster | C42: JD 8.00 | D42: JD 8.00 (co-pay) | E42: Pro Only
A43: Roadside Assistance | B43: 24/7 towing, flat tire, battery, lockout | C43: JD 3.00 | D43: JD 0 (included) | E43: Core + Pro
A45: WHY THIS WORKS FOR INVESTORS:
A46: • Bulk purchasing power: Group policies cost 40-60% less than individual driver policies
A47: • Retention driver: Insurance benefits create switching costs — drivers lose coverage if they leave
A48: • Regulatory compliance: Mandatory liability baked into platform cost, not optional
A49: • Upsell path: Starter drivers see insurance value in Core/Pro and upgrade over time
A50: • Revenue protection: Lower churn from insurance lock-in improves LTV and payback period
A52: COMPETITIVE POSITIONING vs. UBER/CAREEM IN AMMAN
A53: Metric | B53: Uber/Careem (Amman) | C53: Wasel (Blended) | D53: Driver Advantage
A54: Commission / Fee Model | B54: 30% per ride | C54: Flat monthly fee | D54: Predictable cost
A55: Driver keeps (% of fare) | B55: 0.7 | C55: 1 | D55: +30% more per ride
A56: Effective cost on JD 585/mo revenue (Core) | B56: =585*0.3 -> 175.5 | C56: =Assumptions!B50 -> 32.25 | D56: =B56-C56 -> 143.25
A57: Insurance included? | B57: No | C57: Yes (all tiers) | D57: Added value
A58: Maintenance benefits? | B58: No | C58: Pro tier | D58: Cost savings for driver
A59: Cash payment support? | B59: Limited | C59: Full (65% cash) | D59: Fits Jordan market
A60: Switching cost for driver | B60: None | C60: Insurance + benefits | D60: Higher retention

Sheet Monthly P&L
A1: WASEL — 12-MONTH PROJECTED P&L
A2: All figures in Jordanian Dinars (JOD) | Cohort-based driver model with graduated onboarding
A4: Line Item | B4: Type | C4: Month 1 | D4: Month 2 | E4: Month 3 | F4: Month 4 | G4: Month 5 | H4: Month 6 | I4: Month 7 | J4: Month 8 | K4: Month 9 | L4: Month 10 | M4: Month 11 | N4: Month 12 | O4: YEAR 1 TOTAL
A5: DRIVER METRICS (COHORT-BASED)
A6: New Drivers Added | B6: Calc | C6: =Assumptions!B28 -> 250 | D6: =ROUND(C11*Assumptions!$B$29,0) -> 70 | E6: =ROUND(D11*Assumptions!$B$29,0) -> 72 | F6: =ROUND(E11*Assumptions!$B$29,0) -> 81 | G6: =ROUND(F11*Assumptions!$B$29,0) -> 95 | H6: =ROUND(G11*Assumptions!$B$29,0) -> 112 | I6: =ROUND(H11*Assumptions!$B$29,0) -> 132 | J6: =ROUND(I11*Assumptions!$B$29,0) -> 155 | K6: =ROUND(J11*Assumptions!$B$29,0) -> 183 | ... N6: =ROUND(M11*Assumptions!$B$29,0) -> 298 | O6: =SUM(C6:N6) -> 1916
A7: M0 Drivers (Trial — JD 0 fee) | B7: Cohort | C7: =C6 -> 250 | D7: =D6 -> 70 | E7: =E6 -> 72 | F7: =F6 -> 81 | G7: =G6 -> 95 | H7: =H6 -> 112 | I7: =I6 -> 132 | J7: =J6 -> 155 | ... N7: =N6 -> 298 | O7: =N7 -> 298
A8: M1 Drivers (Ramp — JD 10 fee) | B8: Cohort | C8: 0 | D8: =ROUND(C7*(1-Assumptions!$B$40),0) -> 188 | E8: =ROUND(D7*(1-Assumptions!$B$40),0) -> 53 | F8: =ROUND(E7*(1-Assumptions!$B$40),0) -> 54 | G8: =ROUND(F7*(1-Assumptions!$B$40),0) -> 61 | H8: =ROUND(G7*(1-Assumptions!$B$40),0) -> 71 | I8: =ROUND(H7*(1-Assumptions!$B$40),0) -> 84 | J8: =ROUND(I7*(1-Assumptions!$B$40),0) -> 99 | K8: =ROUND(J7*(1-Assumptions!$B$40),0) -> 116 | ... N8: =ROUND(M7*(1-Assumptions!$B$40),0) -> 190 | O8: =N8 -> 190
A9: M2+ Drivers (Active — tier pricing) | B9: Cohort | C9: 0 | D9: =ROUND(C8*(1-Assumptions!$B$41),0)+ROUND(C9*(1-Assumptions!$B$42),0) -> 0 | E9: =ROUND(D8*(1-Assumptions!$B$41),0)+ROUND(D9*(1-Assumptions!$B$42),0) -> 165 | F9: =ROUND(E8*(1-Assumptions!$B$41),0)+ROUND(E9*(1-Assumptions!$B$42),0) -> 205 | G9: =ROUND(F8*(1-Assumptions!$B$41),0)+ROUND(F9*(1-Assumptions!$B$42),0) -> 245 | H9: =ROUND(G8*(1-Assumptions!$B$41),0)+ROUND(G9*(1-Assumptions!$B$42),0) -> 289 | I9: =ROUND(H8*(1-Assumptions!$B$41),0)+ROUND(H9*(1-Assumptions!$B$42),0) -> 339 | J9: =ROUND(I8*(1-Assumptions!$B$41),0)+ROUND(I9*(1-Assumptions!$B$42),0) -> 399 | K9: =ROUND(J8*(1-Assumptions!$B$41),0)+ROUND(J9*(1-Assumptions!$B$42),0) -> 470 | ... N9: =ROUND(M8*(1-Assumptions!$B$41),0)+ROUND(M9*(1-Assumptions!$B$42),0) -> 768 | O9: =N9 -> 768
A10: Churned Drivers | B10: Calc | C10: 0 | D10: =ROUND(C7*Assumptions!$B$40,0)+ROUND(C8*Assumptions!$B$41,0)+ROUND(C9*Assumptions!$B$42,0) -> 63 | E10: =ROUND(D7*Assumptions!$B$40,0)+ROUND(D8*Assumptions!$B$41,0)+ROUND(D9*Assumptions!$B$42,0) -> 41 | F10: =ROUND(E7*Assumptions!$B$40,0)+ROUND(E8*Assumptions!$B$41,0)+ROUND(E9*Assumptions!$B$42,0) -> 31 | G10: =ROUND(F7*Assumptions!$B$40,0)+ROUND(F8*Assumptions!$B$41,0)+ROUND(F9*Assumptions!$B$42,0) -> 34 | H10: =ROUND(G7*Assumptions!$B$40,0)+ROUND(G8*Assumptions!$B$41,0)+ROUND(G9*Assumptions!$B$42,0) -> 41 | I10: =ROUND(H7*Assumptions!$B$40,0)+ROUND(H8*Assumptions!$B$41,0)+ROUND(H9*Assumptions!$B$42,0) -> 49 | J10: =ROUND(I7*Assumptions!$B$40,0)+ROUND(I8*Assumptions!$B$41,0)+ROUND(I9*Assumptions!$B$42,0) -> 57 | K10: =ROUND(J7*Assumptions!$B$40,0)+ROUND(J8*Assumptions!$B$41,0)+ROUND(J9*Assumptions!$B$42,0) -> 67 | ... N10: =ROUND(M7*Assumptions!$B$40,0)+ROUND(M8*Assumptions!$B$41,0)+ROUND(M9*Assumptions!$B$42,0) -> 108 | O10: =SUM(C10:N10) -> 662
A11: Total Active Drivers (EoM) | B11: Sum | C11: =C7+C8+C9 -> 250 | D11: =D7+D8+D9 -> 258 | E11: =E7+E8+E9 -> 290 | F11: =F7+F8+F9 -> 340 | G11: =G7+G8+G9 -> 401 | H11: =H7+H8+H9 -> 472 | I11: =I7+I8+I9 -> 555 | J11: =J7+J8+J9 -> 653 | ... N11: =N7+N8+N9 -> 1256 | O11: =N11 -> 1256
A12: Total Rides (month) | B12: Calc | C12: =C11*Assumptions!$B$9*Assumptions!$B$10 -> 58500 | D12: =D11*Assumptions!$B$9*Assumptions!$B$10 -> 60372 | E12: =E11*Assumptions!$B$9*Assumptions!$B$10 -> 67860 | F12: =F11*Assumptions!$B$9*Assumptions!$B$10 -> 79560 | G12: =G11*Assumptions!$B$9*Assumptions!$B$10 -> 93834 | H12: =H11*Assumptions!$B$9*Assumptions!$B$10 -> 110448 | I12: =I11*Assumptions!$B$9*Assumptions!$B$10 -> 129870 | J12: =J11*Assumptions!$B$9*Assumptions!$B$10 -> 152802 | ... N12: =N11*Assumptions!$B$9*Assumptions!$B$10 -> 293904 | O12: =SUM(C12:N12) -> 1688310
A13: Gross Ride GMV (platform volume) | B13: Calc | C13: =C12*Assumptions!$B$8 -> 138645 | D13: =D12*Assumptions!$B$8 -> 143081.64 | E13: =E12*Assumptions!$B$8 -> 160828.2 | F13: =F12*Assumptions!$B$8 -> 188557.2 | G13: =G12*Assumptions!$B$8 -> 222386.58 | H13: =H12*Assumptions!$B$8 -> 261761.76 | I13: =I12*Assumptions!$B$8 -> 307791.9 | J13: =J12*Assumptions!$B$8 -> 362140.74 | ... N13: =N12*Assumptions!$B$8 -> 696552.48 | O13: =SUM(C13:N13) -> 4001294.7
A15: REVENUE
A16: M0 Revenue (Trial — JD 0) | B16: Calc | C16: 0 | D16: 0 | E16: 0 | F16: 0 | G16: 0 | H16: 0 | I16: 0 | J16: 0 | K16: 0 | L16: 0 | M16: 0 | N16: 0 | O16: =SUM(C16:N16) -> 0
A17: M1 Revenue (Ramp — JD 10) | B17: Calc | C17: =C8*Assumptions!$C$35 -> 0 | D17: =D8*Assumptions!$C$35 -> 1880 | E17: =E8*Assumptions!$C$35 -> 530 | F17: =F8*Assumptions!$C$35 -> 540 | G17: =G8*Assumptions!$C$35 -> 610 | H17: =H8*Assumptions!$C$35 -> 710 | I17: =I8*Assumptions!$C$35 -> 840 | J17: =J8*Assumptions!$C$35 -> 990 | ... N17: =N8*Assumptions!$C$35 -> 1900 | O17: =SUM(C17:N17) -> 12140
A18: M2+ Starter Tier Subscriptions | B18: Calc | C18: =C9*Assumptions!$D$47*Assumptions!$B$47 -> 0 | D18: =D9*Assumptions!$D$47*Assumptions!$B$47 -> 0 | E18: =E9*Assumptions!$D$47*Assumptions!$B$47 -> 1485 | F18: =F9*Assumptions!$D$47*Assumptions!$B$47 -> 1845 | G18: =G9*Assumptions!$D$47*Assumptions!$B$47 -> 2205 | H18: =H9*Assumptions!$D$47*Assumptions!$B$47 -> 2601 | I18: =I9*Assumptions!$D$47*Assumptions!$B$47 -> 3051 | J18: =J9*Assumptions!$D$47*Assumptions!$B$47 -> 3591 | ... N18: =N9*Assumptions!$D$47*Assumptions!$B$47 -> 6912 | O18: =SUM(C18:N18) -> 36765
A19: M2+ Core Tier Subscriptions | B19: Calc | C19: =C9*Assumptions!$D$48*Assumptions!$B$48 -> 0 | D19: =D9*Assumptions!$D$48*Assumptions!$B$48 -> 0 | E19: =E9*Assumptions!$D$48*Assumptions!$B$48 -> 2021.25 | F19: =F9*Assumptions!$D$48*Assumptions!$B$48 -> 2511.25 | G19: =G9*Assumptions!$D$48*Assumptions!$B$48 -> 3001.25 | H19: =H9*Assumptions!$D$48*Assumptions!$B$48 -> 3540.25 | I19: =I9*Assumptions!$D$48*Assumptions!$B$48 -> 4152.75 | J19: =J9*Assumptions!$D$48*Assumptions!$B$48 -> 4887.75 | ... N19: =N9*Assumptions!$D$48*Assumptions!$B$48 -> 9408 | O19: =SUM(C19:N19) -> 50041.25
A20: M2+ Pro Tier Subscriptions | B20: Calc | C20: =C9*Assumptions!$D$49*Assumptions!$B$49 -> 0 | D20: =D9*Assumptions!$D$49*Assumptions!$B$49 -> 0 | E20: =E9*Assumptions!$D$49*Assumptions!$B$49 -> 1815 | F20: =F9*Assumptions!$D$49*Assumptions!$B$49 -> 2255 | G20: =G9*Assumptions!$D$49*Assumptions!$B$49 -> 2695 | H20: =H9*Assumptions!$D$49*Assumptions!$B$49 -> 3179 | I20: =I9*Assumptions!$D$49*Assumptions!$B$49 -> 3729 | J20: =J9*Assumptions!$D$49*Assumptions!$B$49 -> 4389 | ... N20: =N9*Assumptions!$D$49*Assumptions!$B$49 -> 8448 | O20: =SUM(C20:N20) -> 44935
A21: Total Subscription Revenue | B21: Sum | C21: =SUM(C16:C20) -> 0 | D21: =SUM(D16:D20) -> 1880 | E21: =SUM(E16:E20) -> 5851.25 | F21: =SUM(F16:F20) -> 7151.25 | G21: =SUM(G16:G20) -> 8511.25 | H21: =SUM(H16:H20) -> 10030.25 | I21: =SUM(I16:I20) -> 11772.75 | J21: =SUM(J16:J20) -> 13857.75 | ... N21: =SUM(N16:N20) -> 26668 | O21: =SUM(C21:N21) -> 143881.25
A23: TOTAL REVENUE | B23: Sum | C23: =C21 -> 0 | D23: =D21 -> 1880 | E23: =E21 -> 5851.25 | F23: =F21 -> 7151.25 | G23: =G21 -> 8511.25 | H23: =H21 -> 10030.25 | I23: =I21 -> 11772.75 | J23: =J21 -> 13857.75 | ... N23: =N21 -> 26668 | O23: =SUM(C23:N23) -> 143881.25
A25: COST OF REVENUE (VARIABLE)
A26: Payment Processing Fees (Digital Subs) | B26: Calc | C26: =C23*Assumptions!$B$13*Assumptions!$B$14 -> 0 | D26: =D23*Assumptions!$B$13*Assumptions!$B$14 -> 19.74 | E26: =E23*Assumptions!$B$13*Assumptions!$B$14 -> 61.438125 | F26: =F23*Assumptions!$B$13*Assumptions!$B$14 -> 75.088125 | G26: =G23*Assumptions!$B$13*Assumptions!$B$14 -> 89.368125 | H26: =H23*Assumptions!$B$13*Assumptions!$B$14 -> 105.31762 | I26: =I23*Assumptions!$B$13*Assumptions!$B$14 -> 123.61387 | J26: =J23*Assumptions!$B$13*Assumptions!$B$14 -> 145.50637 | ... N26: =N23*Assumptions!$B$13*Assumptions!$B$14 -> 280.014 | O26: =SUM(C26:N26) -> 1510.7531
A27: Insurance Program Costs | B27: Calc | C27: =C11*Assumptions!$B$59 -> 2162.5 | D27: =D11*Assumptions!$B$59 -> 2231.7 | E27: =E11*Assumptions!$B$59 -> 2508.5 | F27: =F11*Assumptions!$B$59 -> 2941 | G27: =G11*Assumptions!$B$59 -> 3468.65 | H27: =H11*Assumptions!$B$59 -> 4082.8 | I27: =I11*Assumptions!$B$59 -> 4800.75 | J27: =J11*Assumptions!$B$59 -> 5648.45 | ... N27: =N11*Assumptions!$B$59 -> 10864.4 | O27: =SUM(C27:N27) -> 62409.75
A28: Cloud Infrastructure (AWS/Firebase) | B28: Semi-Fix | C28: =Assumptions!$B$63*(C11/Assumptions!$B$28)^0.5 -> 800 | D28: =Assumptions!$B$63*(D11/Assumptions!$B$28)^0.5 -> 812.69921 | E28: =Assumptions!$B$63*(E11/Assumptions!$B$28)^0.5 -> 861.62637 | F28: =Assumptions!$B$63*(F11/Assumptions!$B$28)^0.5 -> 932.9523 | G28: =Assumptions!$B$63*(G11/Assumptions!$B$28)^0.5 -> 1013.193 | H28: =Assumptions!$B$63*(H11/Assumptions!$B$28)^0.5 -> 1099.2361 | I28: =Assumptions!$B$63*(I11/Assumptions!$B$28)^0.5 -> 1191.9732 | J28: =Assumptions!$B$63*(J11/Assumptions!$B$28)^0.5 -> 1292.9346 | ... N28: =Assumptions!$B$63*(N11/Assumptions!$B$28)^0.5 -> 1793.1425 | O28: =SUM(C28:N28) -> 14374.9
A29: Maps & Location API | B29: Variable | C29: =Assumptions!$B$64*(C11/Assumptions!$B$28) -> 400 | D29: =Assumptions!$B$64*(D11/Assumptions!$B$28) -> 412.8 | E29: =Assumptions!$B$64*(E11/Assumptions!$B$28) -> 464 | F29: =Assumptions!$B$64*(F11/Assumptions!$B$28) -> 544 | G29: =Assumptions!$B$64*(G11/Assumptions!$B$28) -> 641.6 | H29: =Assumptions!$B$64*(H11/Assumptions!$B$28) -> 755.2 | I29: =Assumptions!$B$64*(I11/Assumptions!$B$28) -> 888 | J29: =Assumptions!$B$64*(J11/Assumptions!$B$28) -> 1044.8 | ... N29: =Assumptions!$B$64*(N11/Assumptions!$B$28) -> 2009.6 | O29: =SUM(C29:N29) -> 11544
A30: SMS / Push Notifications | B30: Variable | C30: =Assumptions!$B$65*(C11/Assumptions!$B$28) -> 200 | D30: =Assumptions!$B$65*(D11/Assumptions!$B$28) -> 206.4 | E30: =Assumptions!$B$65*(E11/Assumptions!$B$28) -> 232 | F30: =Assumptions!$B$65*(F11/Assumptions!$B$28) -> 272 | G30: =Assumptions!$B$65*(G11/Assumptions!$B$28) -> 320.8 | H30: =Assumptions!$B$65*(H11/Assumptions!$B$28) -> 377.6 | I30: =Assumptions!$B$65*(I11/Assumptions!$B$28) -> 444 | J30: =Assumptions!$B$65*(J11/Assumptions!$B$28) -> 522.4 | ... N30: =Assumptions!$B$65*(N11/Assumptions!$B$28) -> 1004.8 | O30: =SUM(C30:N30) -> 5772
A31: Driver Onboarding & Verification | B31: Per New | C31: =C6*Assumptions!$B$67 -> 3750 | D31: =D6*Assumptions!$B$67 -> 1050 | E31: =E6*Assumptions!$B$67 -> 1080 | F31: =F6*Assumptions!$B$67 -> 1215 | G31: =G6*Assumptions!$B$67 -> 1425 | H31: =H6*Assumptions!$B$67 -> 1680 | I31: =I6*Assumptions!$B$67 -> 1980 | J31: =J6*Assumptions!$B$67 -> 2325 | ... N31: =N6*Assumptions!$B$67 -> 4470 | O31: =SUM(C31:N31) -> 28740
A32: Total Cost of Revenue | B32: Sum | C32: =SUM(C26:C31) -> 7312.5 | D32: =SUM(D26:D31) -> 4733.3392 | E32: =SUM(E26:E31) -> 5207.5645 | F32: =SUM(F26:F31) -> 5980.0404 | G32: =SUM(G26:G31) -> 6958.6111 | H32: =SUM(H26:H31) -> 8100.1537 | I32: =SUM(I26:I31) -> 9428.337 | J32: =SUM(J26:J31) -> 10979.091 | ... N32: =SUM(N26:N31) -> 20421.956 | O32: =SUM(C32:N32) -> 124351.4
A34: GROSS PROFIT | B34: Calc | C34: =C23-C32 -> -7312.5 | D34: =D23-D32 -> -2853.3392 | E34: =E23-E32 -> 643.68551 | F34: =F23-F32 -> 1171.2096 | G34: =G23-G32 -> 1552.6389 | H34: =H23-H32 -> 1930.0963 | I34: =I23-I32 -> 2344.413 | J34: =J23-J32 -> 2878.659 | ... N34: =N23-N32 -> 6246.0435 | O34: =SUM(C34:N34) -> 19529.847
A35: Gross Margin % | B35: % | C35: =IF(C23=0,0,C34/C23) -> 0 | D35: =IF(D23=0,0,D34/D23) -> -1.5177336 | E35: =IF(E23=0,0,E34/E23) -> 0.1100082 | F35: =IF(F23=0,0,F34/F23) -> 0.1637769 | G35: =IF(G23=0,0,G34/G23) -> 0.18242196 | H35: =IF(H23=0,0,H34/H23) -> 0.19242753 | I35: =IF(I23=0,0,I34/I23) -> 0.19913894 | J35: =IF(J23=0,0,J34/J23) -> 0.20772918 | ... O35: =IF(O23=0,0,O34/O23) -> 0.13573587
A37: OPERATING EXPENSES (OPEX)
A38: Team & Overhead (Salaries + Office) | B38: Fixed | C38: =Assumptions!$C$87 -> 7500 | D38: =Assumptions!$C$87 -> 7500 | E38: =Assumptions!$C$87 -> 7500 | F38: =Assumptions!$C$87 -> 7500 | G38: =Assumptions!$C$87 -> 7500 | H38: =Assumptions!$C$87 -> 7500 | I38: =Assumptions!$C$87 -> 7500 | J38: =Assumptions!$C$87 -> 7500 | ... N38: =Assumptions!$C$87 -> 7500 | O38: =SUM(C38:N38) -> 90000
A39: Customer Support | B39: Semi-Fix | C39: =Assumptions!$B$66*(C11/Assumptions!$B$28) -> 1500 | D39: =Assumptions!$B$66*(D11/Assumptions!$B$28) -> 1548 | E39: =Assumptions!$B$66*(E11/Assumptions!$B$28) -> 1740 | F39: =Assumptions!$B$66*(F11/Assumptions!$B$28) -> 2040 | G39: =Assumptions!$B$66*(G11/Assumptions!$B$28) -> 2406 | H39: =Assumptions!$B$66*(H11/Assumptions!$B$28) -> 2832 | I39: =Assumptions!$B$66*(I11/Assumptions!$B$28) -> 3330 | J39: =Assumptions!$B$66*(J11/Assumptions!$B$28) -> 3918 | ... N39: =Assumptions!$B$66*(N11/Assumptions!$B$28) -> 7536 | O39: =SUM(C39:N39) -> 43290
A40: Marketing — Driver Acquisition | B40: Variable | C40: =C6*Assumptions!$B$68 -> 7500 | D40: =D6*Assumptions!$B$68 -> 2100 | E40: =E6*Assumptions!$B$68 -> 2160 | F40: =F6*Assumptions!$B$68 -> 2430 | G40: =G6*Assumptions!$B$68 -> 2850 | H40: =H6*Assumptions!$B$68 -> 3360 | I40: =I6*Assumptions!$B$68 -> 3960 | J40: =J6*Assumptions!$B$68 -> 4650 | ... N40: =N6*Assumptions!$B$68 -> 8940 | O40: =SUM(C40:N40) -> 57480
A41: Rider Acquisition & Promos | B41: Fixed | C41: =Assumptions!$B$69 -> 3000 | D41: =Assumptions!$B$69 -> 3000 | E41: =Assumptions!$B$69 -> 3000 | F41: =Assumptions!$B$69 -> 3000 | G41: =Assumptions!$B$69 -> 3000 | H41: =Assumptions!$B$69 -> 3000 | I41: =Assumptions!$B$69 -> 3000 | J41: =Assumptions!$B$69 -> 3000 | ... N41: =Assumptions!$B$69 -> 3000 | O41: =SUM(C41:N41) -> 36000
A42: Regulatory & LTRC License Fee | B42: Fixed | C42: =Assumptions!$C$98 -> 11083.333 | D42: =Assumptions!$C$98 -> 11083.333 | E42: =Assumptions!$C$98 -> 11083.333 | F42: =Assumptions!$C$98 -> 11083.333 | G42: =Assumptions!$C$98 -> 11083.333 | H42: =Assumptions!$C$98 -> 11083.333 | I42: =Assumptions!$C$98 -> 11083.333 | J42: =Assumptions!$C$98 -> 11083.333 | ... N42: =Assumptions!$C$98 -> 11083.333 | O42: =SUM(C42:N42) -> 133000
A43: Legal & Accounting | B43: Fixed | C43: =Assumptions!$C$85 -> 400 | D43: =Assumptions!$C$85 -> 400 | E43: =Assumptions!$C$85 -> 400 | F43: =Assumptions!$C$85 -> 400 | G43: =Assumptions!$C$85 -> 400 | H43: =Assumptions!$C$85 -> 400 | I43: =Assumptions!$C$85 -> 400 | J43: =Assumptions!$C$85 -> 400 | ... N43: =Assumptions!$C$85 -> 400 | O43: =SUM(C43:N43) -> 4800
A44: OPEX Variance Adjustment | B44: Adj | C44: =SUM(C38:C43)*IF(COLUMN(C38)-COLUMN($B$38)<=1,Assumptions!$B$73,IF(COLUMN(C38)-COLUMN($B$38)<=4,Assumptions!$B$74,Assumptions!$B$75)) -> 4647.5 | D44: =SUM(D38:D43)*IF(COLUMN(D38)-COLUMN($B$38)<=1,Assumptions!$B$73,IF(COLUMN(D38)-COLUMN($B$38)<=4,Assumptions!$B$74,Assumptions!$B$75)) -> 1794.1933 | E44: =SUM(E38:E43)*IF(COLUMN(E38)-COLUMN($B$38)<=1,Assumptions!$B$73,IF(COLUMN(E38)-COLUMN($B$38)<=4,Assumptions!$B$74,Assumptions!$B$75)) -> 1811.8333 | F44: =SUM(F38:F43)*IF(COLUMN(F38)-COLUMN($B$38)<=1,Assumptions!$B$73,IF(COLUMN(F38)-COLUMN($B$38)<=4,Assumptions!$B$74,Assumptions!$B$75)) -> 1851.7333 | G44: =SUM(G38:G43)*IF(COLUMN(G38)-COLUMN($B$38)<=1,Assumptions!$B$73,IF(COLUMN(G38)-COLUMN($B$38)<=4,Assumptions!$B$74,Assumptions!$B$75)) -> 2723.9333 | H44: =SUM(H38:H43)*IF(COLUMN(H38)-COLUMN($B$38)<=1,Assumptions!$B$73,IF(COLUMN(H38)-COLUMN($B$38)<=4,Assumptions!$B$74,Assumptions!$B$75)) -> 2817.5333 | I44: =SUM(I38:I43)*IF(COLUMN(I38)-COLUMN($B$38)<=1,Assumptions!$B$73,IF(COLUMN(I38)-COLUMN($B$38)<=4,Assumptions!$B$74,Assumptions!$B$75)) -> 2927.3333 | J44: =SUM(J38:J43)*IF(COLUMN(J38)-COLUMN($B$38)<=1,Assumptions!$B$73,IF(COLUMN(J38)-COLUMN($B$38)<=4,Assumptions!$B$74,Assumptions!$B$75)) -> 3055.1333 | ... N44: =SUM(N38:N43)*IF(COLUMN(N38)-COLUMN($B$38)<=1,Assumptions!$B$73,IF(COLUMN(N38)-COLUMN($B$38)<=4,Assumptions!$B$74,Assumptions!$B$75)) -> 3845.9333 | O44: =SUM(C44:N44) -> 35667.127
A45: Total Operating Expenses | B45: Sum | C45: =SUM(C38:C44) -> 35630.833 | D45: =SUM(D38:D44) -> 27425.527 | E45: =SUM(E38:E44) -> 27695.167 | F45: =SUM(F38:F44) -> 28305.067 | G45: =SUM(G38:G44) -> 29963.267 | H45: =SUM(H38:H44) -> 30992.867 | I45: =SUM(I38:I44) -> 32200.667 | J45: =SUM(J38:J44) -> 33606.467 | ... N45: =SUM(N38:N44) -> 42305.267 | O45: =SUM(C45:N45) -> 400237.13
A47: EBITDA | B47: Calc | C47: =C34-C45 -> -42943.333 | D47: =D34-D45 -> -30278.866 | E47: =E34-E45 -> -27051.481 | F47: =F34-F45 -> -27133.857 | G47: =G34-G45 -> -28410.628 | H47: =H34-H45 -> -29062.77 | I47: =I34-I45 -> -29856.254 | J47: =J34-J45 -> -30727.808 | ... N47: =N34-N45 -> -36059.223 | O47: =SUM(C47:N47) -> -380707.28
A48: EBITDA Margin % | B48: % | C48: =IF(C23=0,0,C47/C23) -> 0 | D48: =IF(D23=0,0,D47/D23) -> -16.10578 | E48: =IF(E23=0,0,E47/E23) -> -4.623197 | F48: =IF(F23=0,0,F47/F23) -> -3.7942817 | G48: =IF(G23=0,0,G47/G23) -> -3.3380088 | H48: =IF(H23=0,0,H47/H23) -> -2.8975121 | I48: =IF(I23=0,0,I47/I23) -> -2.5360475 | J48: =IF(J23=0,0,J47/J23) -> -2.2173735 | ... O48: =IF(O23=0,0,O47/O23) -> -2.6459826
A50: Depreciation & Amortization | B50: Fixed | C50: =Assumptions!$B$102/36 -> 972.22222 | D50: =Assumptions!$B$102/36 -> 972.22222 | E50: =Assumptions!$B$102/36 -> 972.22222 | F50: =Assumptions!$B$102/36 -> 972.22222 | G50: =Assumptions!$B$102/36 -> 972.22222 | H50: =Assumptions!$B$102/36 -> 972.22222 | I50: =Assumptions!$B$102/36 -> 972.22222 | J50: =Assumptions!$B$102/36 -> 972.22222 | ... N50: =Assumptions!$B$102/36 -> 972.22222 | O50: =SUM(C50:N50) -> 11666.667
A51: Interest Expense | B51: Fixed | C51: 0 | D51: 0 | E51: 0 | F51: 0 | G51: 0 | H51: 0 | I51: 0 | J51: 0 | K51: 0 | L51: 0 | M51: 0 | N51: 0 | O51: =SUM(C51:N51) -> 0
A53: NET INCOME (LOSS) | B53: Calc | C53: =C47-C50-C51 -> -43915.556 | D53: =D47-D50-D51 -> -31251.088 | E53: =E47-E50-E51 -> -28023.703 | F53: =F47-F50-F51 -> -28106.079 | G53: =G47-G50-G51 -> -29382.85 | H53: =H47-H50-H51 -> -30034.993 | I53: =I47-I50-I51 -> -30828.476 | J53: =J47-J50-J51 -> -31700.03 | ... N53: =N47-N50-N51 -> -37031.445 | O53: =SUM(C53:N53) -> -392373.95
A54: Net Margin % | B54: % | C54: =IF(C23=0,0,C53/C23) -> 0 | D54: =IF(D23=0,0,D53/D23) -> -16.622919 | E54: =IF(E23=0,0,E53/E23) -> -4.7893533 | F54: =IF(F23=0,0,F53/F23) -> -3.9302331 | G54: =IF(G23=0,0,G53/G23) -> -3.4522367 | H54: =IF(H23=0,0,H53/H23) -> -2.9944411 | I54: =IF(I23=0,0,I53/I23) -> -2.61863 | J54: =IF(J23=0,0,J53/J23) -> -2.2875308 | ... O54: =IF(O23=0,0,O53/O23) -> -2.727068
A56: Cumulative Net Income (Loss) | B56: Calc | C56: =C53 -> -43915.556 | D56: =C56+D53 -> -75166.644 | E56: =D56+E53 -> -103190.35 | F56: =E56+F53 -> -131296.43 | G56: =F56+G53 -> -160679.28 | H56: =G56+H53 -> -190714.27 | I56: =H56+I53 -> -221542.74 | J56: =I56+J53 -> -253242.77 | K56: =J56+K53 -> -286010.43 | ... N56: =M56+N53 -> -392373.95 | O56: =N56 -> -392373.95

Sheet Unit Economics
A1: UNIT ECONOMICS — PER-DRIVER ANALYSIS
A2: All figures in Jordanian Dinars (JOD) per driver per month | Updated for 3-tier model with transition churn
A4: DRIVER ECONOMICS (GROSS FARE INCOME)
A5: Metric | B5: Starter | C5: Core | D5: Pro | E5: Blended Avg
A6: Trips/Day (Soft-Cap) | B6: =Assumptions!E47 -> 8 | C6: =Assumptions!E48 -> 9 | D6: =Assumptions!E49 -> 12 | E6: =Assumptions!B9 -> 9
A7: Monthly Gross Fare Revenue (JOD) | B7: =Assumptions!F47 -> 492.96 | C7: =Assumptions!F48 -> 554.58 | D7: =Assumptions!F49 -> 739.44 | E7: =Assumptions!B11 -> 554.58
A8: (−) Driver Operating Costs | B8: =-Assumptions!B22 -> -350 | C8: =-Assumptions!B22 -> -350 | D8: =-Assumptions!B22 -> -350 | E8: =-Assumptions!B22 -> -350 | F8: Fuel JD 200 + Maint JD 120 + Data JD 30
A9: (−) Wasel Subscription Fee | B9: =-Assumptions!B47 -> -20 | C9: =-Assumptions!B48 -> -35 | D9: =-Assumptions!B49 -> -55 | E9: =-Assumptions!B50 -> -32.25
A10: Net Driver Take-Home Income | B10: =B7+B8+B9 -> 122.96 | C10: =C7+C8+C9 -> 169.58 | D10: =D7+D8+D9 -> 334.44 | E10: =E7+E8+E9 -> 172.33
A11: Net Income as % of Gross Fare | B11: =B10/B7 -> 0.249432 | C11: =C10/C7 -> 0.30578095 | D11: =D10/D7 -> 0.45228822 | E11: =E10/E7 -> 0.31073966 | F11: vs. 70% at Uber/Careem
A13: PLATFORM REVENUE PER DRIVER (M2+ ACTIVE)
A14: Metric | B14: Starter | C14: Core | D14: Pro | E14: Blended Avg
A15: Monthly Subscription Fee (JOD) | B15: =Assumptions!B47 -> 20 | C15: =Assumptions!B48 -> 35 | D15: =Assumptions!B49 -> 55 | E15: =Assumptions!B50 -> 32.25
A16: Driver Mix % | B16: =Assumptions!D47 -> 0.45 | C16: =Assumptions!D48 -> 0.35 | D16: =Assumptions!D49 -> 0.2 | E16: =SUM(B16:D16) -> 1
A17: ARPU (Avg Revenue Per Driver) | B17: =B15 -> 20 | C17: =C15 -> 35 | D17: =D15 -> 55 | E17: =E15 -> 32.25
A19: PLATFORM COST PER DRIVER
A20: Cost Category | B20: Starter | C20: Core | D20: Pro | E20: Blended Avg
A21: Payment Processing (digital subs) | B21: =B15*Assumptions!$B$13*Assumptions!$B$14 -> 0.21 | C21: =C15*Assumptions!$B$13*Assumptions!$B$14 -> 0.3675 | D21: =D15*Assumptions!$B$13*Assumptions!$B$14 -> 0.5775 | E21: =E15*Assumptions!$B$13*Assumptions!$B$14 -> 0.338625
A22: Insurance — Third-Party Liability | B22: =Assumptions!$B$55 -> 5 | C22: =Assumptions!$B$55 -> 5 | D22: =Assumptions!$B$55 -> 5 | E22: =Assumptions!$B$55 -> 5 | F22: All tiers
A23: Insurance — Comprehensive Subsidy | B23: 0 | C23: 0 | D23: =Assumptions!$B$56 -> 8 | E23: =D23*Assumptions!$D$49 -> 1.6 | F23: Pro only
A24: Roadside Assistance | B24: 0 | C24: =Assumptions!$B$57 -> 3 | D24: =Assumptions!$B$57 -> 3 | E24: =C24*(Assumptions!$D$48+Assumptions!$D$49) -> 1.65 | F24: Core + Pro
A25: Maintenance Network Subsidy | B25: 0 | C25: 0 | D25: =Assumptions!$B$58 -> 2 | E25: =D25*Assumptions!$D$49 -> 0.4 | F25: Pro only
A26: Cloud & Tech Infrastructure (allocated) | B26: =(Assumptions!$B$63+Assumptions!$B$64+Assumptions!$B$65)/Assumptions!$B$28 -> 5.6 | C26: =B26 -> 5.6 | D26: =B26 -> 5.6 | E26: =B26 -> 5.6 | F26: Baseline allocated equally
A27: Total Variable Cost per Driver | B27: =SUM(B21:B26) -> 10.81 | C27: =SUM(C21:C26) -> 13.9675 | D27: =SUM(D21:D26) -> 24.1775 | E27: =SUM(E21:E26) -> 14.588625
A29: CONTRIBUTION MARGIN
A30: Metric | B30: Starter | C30: Core | D30: Pro | E30: Blended Avg
A31: Subscription Revenue | B31: =B17 -> 20 | C31: =C17 -> 35 | D31: =D17 -> 55 | E31: =E17 -> 32.25
A32: (−) Total Variable Cost | B32: =-B27 -> -10.81 | C32: =-C27 -> -13.9675 | D32: =-D27 -> -24.1775 | E32: =-E27 -> -14.588625
A33: Contribution Margin (JOD) | B33: =B31+B32 -> 9.19 | C33: =C31+C32 -> 21.0325 | D33: =D31+D32 -> 30.8225 | E33: =E31+E32 -> 17.661375
A34: Contribution Margin % | B34: =B33/B31 -> 0.4595 | C34: =C33/C31 -> 0.60092857 | D34: =D33/D31 -> 0.56040909 | E34: =E33/E31 -> 0.54763953
A37: DRIVER LIFETIME VALUE (LTV) — TRANSITION CHURN MODEL
A38: Metric | B38: Value | C38: Unit | D38: Source / Notes
A39: Survival Rate: M0 → M1 | B39: =1-Assumptions!B40 -> 0.75 | C39: % | D39: 75% survive first payment wall (improved onboarding)
A40: Survival Rate: M1 → M2 | B40: =1-Assumptions!B41 -> 0.88 | C40: % | D40: 88% survive full-price transition
A41: Monthly Churn (M2–M6) | B41: =Assumptions!B42 -> 0.04 | C41: %/month | D41: 4% monthly churn in early active phase
A42: Monthly Churn (M6+) | B42: =Assumptions!B43 -> 0.02 | C42: %/month | D42: 2% monthly; strong retention with insurance lock-in
A43: Effective Avg Lifespan (months) | B43: =B39*B40*(1+ (1-B41)*4/(1) + (1-B42)*(1/B42)) -> 35.5344 | C43: months | D43: Weighted avg: M0 trial + M1 ramp + M2+ active lifespan
A44: Blended Contribution Margin / Mo | B44: =E33 -> 17.661375 | C44: JOD/mo | D44: Weighted average across all tiers (M2+ active)
A45: Driver LTV (JOD) | B45: =B43*B44 -> 627.58636 | C45: JOD | D45: Contribution Margin × Avg Lifespan
A46: Driver LTV (USD) | B46: =B45*Assumptions!B15 -> 884.89677 | C46: USD
A49: CAC & PAYBACK ANALYSIS
A50: Metric | B50: Value | C50: Unit | D50: Source / Notes
A51: Driver Acquisition Cost (CAC) | B51: =Assumptions!B68 -> 30 | C51: JOD | D51: Referral bonus JD 15 + digital ads JD 10
A52: Driver Onboarding Cost | B52: =Assumptions!B67 -> 15 | C52: JOD | D52: Background check, doc verify, vehicle inspect
A53: Total CAC (Fully Loaded) | B53: =B51+B52 -> 45 | C53: JOD | D53: CAC + onboarding per new driver
A54: LTV / CAC Ratio | B54: =B45/B53 -> 13.946364 | C54: x | D54: Target: >3.0x for healthy unit economics
A55: CAC Payback Period | B55: =B53/B44 -> 2.547933 | C55: months | D55: Months to recover acquisition cost
A58: INVESTOR SCORECARD
A59: KPI | B59: Value | C59: Benchmark | D59: Assessment
A60: LTV / CAC Ratio | B60: =B54 -> 13.946364 | C60: > 3.0x | D60: EXCELLENT
A61: CAC Payback Period | B61: =B55 -> 2.547933 | C61: < 6 months | D61: STRONG
A62: Contribution Margin % | B62: =E34 -> 0.54763953 | C62: > 50% | D62: STRONG

Sheet Cash Flow
A1: WASEL — 12-MONTH CASH FLOW STATEMENT
A2: All figures in Jordanian Dinars (JOD) | Tracks actual cash in/out including pre-launch capital
A4: Line Item | B4: Pre-Launch | C4: Month 1 | D4: Month 2 | E4: Month 3 | F4: Month 4 | G4: Month 5 | H4: Month 6 | I4: Month 7 | J4: Month 8 | K4: Month 9 | L4: Month 10 | M4: Month 11 | N4: Month 12 | O4: TOTAL
A5: CASH INFLOWS
A6: Seed Capital / Founder Investment | B6: =Assumptions!B109 -> 190000 | C6: 0 | D6: 0 | E6: 0 | F6: 0 | G6: 0 | H6: 0 | I6: 0 | J6: 0 | K6: 0 | L6: 0 | M6: 0 | N6: 0 | O6: =SUM(B6:N6) -> 190000
A7: Subscription Revenue (Cash) | B7: 0 | C7: ='Monthly P&L'!C23 -> 0 | D7: ='Monthly P&L'!D23 -> 1880 | E7: ='Monthly P&L'!E23 -> 5851.25 | F7: ='Monthly P&L'!F23 -> 7151.25 | G7: ='Monthly P&L'!G23 -> 8511.25 | H7: ='Monthly P&L'!H23 -> 10030.25 | I7: ='Monthly P&L'!I23 -> 11772.75 | J7: ='Monthly P&L'!J23 -> 13857.75 | ... N7: ='Monthly P&L'!N23 -> 26668 | O7: =SUM(B7:N7) -> 143881.25
A8: Total Cash Inflows | B8: =B6+B7 -> 190000 | C8: =C6+C7 -> 0 | D8: =D6+D7 -> 1880 | E8: =E6+E7 -> 5851.25 | F8: =F6+F7 -> 7151.25 | G8: =G6+G7 -> 8511.25 | H8: =H6+H7 -> 10030.25 | I8: =I6+I7 -> 11772.75 | ... N8: =N6+N7 -> 26668 | O8: =SUM(B8:N8) -> 333881.25
A10: CASH OUTFLOWS
A11: App Development (MVP) | B11: =Assumptions!B102 -> 35000 | C11: 0 | D11: 0 | E11: 0 | F11: 0 | G11: 0 | H11: 0 | I11: 0 | J11: 0 | K11: 0 | L11: 0 | M11: 0 | N11: 0 | O11: =SUM(B11:N11) -> 35000
A12: LTRC License Fee (Upfront) | B12: =Assumptions!B103 -> 100000 | C12: 0 | D12: 0 | E12: 0 | F12: 0 | G12: 0 | H12: 0 | I12: 0 | J12: 0 | K12: 0 | L12: 0 | M12: 0 | N12: 0 | O12: =SUM(B12:N12) -> 100000
A13: Bank Guarantee Deposit | B13: =Assumptions!B104 -> 25000 | C13: 0 | D13: 0 | E13: 0 | F13: 0 | G13: 0 | H13: 0 | I13: 0 | J13: 0 | K13: 0 | L13: 0 | M13: 0 | N13: 0 | O13: =SUM(B13:N13) -> 0
A14: Company Registration & Legal | B14: =Assumptions!B105 -> 5000 | C14: 0 | D14: 0 | E14: 0 | F14: 0 | G14: 0 | H14: 0 | I14: 0 | J14: 0 | K14: 0 | L14: 0 | M14: 0 | N14: 0 | O14: =SUM(B14:N14) -> 5000
A15: Pre-Launch Marketing | B15: =Assumptions!B106 -> 10000 | C15: 0 | D15: 0 | E15: 0 | F15: 0 | G15: 0 | H15: 0 | I15: 0 | J15: 0 | K15: 0 | L15: 0 | M15: 0 | N15: 0 | O15: =SUM(B15:N15) -> 10000
A17: Cost of Revenue (Variable) | B17: 0 | C17: ='Monthly P&L'!C32 -> 7312.5 | D17: ='Monthly P&L'!D32 -> 4733.3392 | E17: ='Monthly P&L'!E32 -> 5207.5645 | F17: ='Monthly P&L'!F32 -> 5980.0404 | G17: ='Monthly P&L'!G32 -> 6958.6111 | H17: ='Monthly P&L'!H32 -> 8100.1537 | I17: ='Monthly P&L'!I32 -> 9428.337 | J17: ='Monthly P&L'!J32 -> 10979.091 | ... N17: ='Monthly P&L'!N32 -> 20421.956 | O17: =SUM(B17:N17) -> 124351.4
A18: Operating Expenses (Fixed + Semi) | B18: 0 | C18: ='Monthly P&L'!C45 -> 35630.833 | D18: ='Monthly P&L'!D45 -> 27425.527 | E18: ='Monthly P&L'!E45 -> 27695.167 | F18: ='Monthly P&L'!F45 -> 28305.067 | G18: ='Monthly P&L'!G45 -> 29963.267 | H18: ='Monthly P&L'!H45 -> 30992.867 | I18: ='Monthly P&L'!I45 -> 32200.667 | J18: ='Monthly P&L'!J45 -> 33606.467 | ... N18: ='Monthly P&L'!N45 -> 42305.267 | O18: =SUM(B18:N18) -> 400237.13
A19: Total Cash Outflows | B19: =SUM(B11:B18) -> 150000 | C19: =SUM(C11:C18) -> 42943.333 | D19: =SUM(D11:D18) -> 32158.866 | E19: =SUM(E11:E18) -> 32902.731 | F19: =SUM(F11:F18) -> 34285.107 | G19: =SUM(G11:G18) -> 36921.878 | H19: =SUM(H11:H18) -> 39093.02 | I19: =SUM(I11:I18) -> 41629.004 | ... N19: =SUM(N11:N18) -> 62727.223 | O19: =SUM(B19:N19) -> 674588.53
A21: NET CASH FLOW | B21: =B8-B19 -> 40000 | C21: =C8-C19 -> -42943.333 | D21: =D8-D19 -> -30278.866 | E21: =E8-E19 -> -27051.481 | F21: =F8-F19 -> -27133.857 | G21: =G8-G19 -> -28410.628 | H21: =H8-H19 -> -29062.77 | I21: =I8-I19 -> -29856.254 | ... N21: =N8-N19 -> -36059.223 | O21: =SUM(B21:N21) -> -340707.28
A23: Opening Cash Balance | B23: 0 | C23: =B25 -> 40000 | D23: =C25 -> -2943.3333 | E23: =D25 -> -33222.199 | F23: =E25 -> -60273.68 | G23: =F25 -> -87407.537 | H23: =G25 -> -115818.17 | I23: =H25 -> -144880.94 | J23: =I25 -> -174737.19 | ... N23: =M25 -> -304648.06
A24: Net Cash Flow | B24: =B21 -> 40000 | C24: =C21 -> -42943.333 | D24: =D21 -> -30278.866 | E24: =E21 -> -27051.481 | F24: =F21 -> -27133.857 | G24: =G21 -> -28410.628 | H24: =H21 -> -29062.77 | I24: =I21 -> -29856.254 | ... N24: =N21 -> -36059.223
A25: CLOSING CASH BALANCE | B25: =B23+B24 -> 40000 | C25: =C23+C24 -> -2943.3333 | D25: =D23+D24 -> -33222.199 | E25: =E23+E24 -> -60273.68 | F25: =F23+F24 -> -87407.537 | G25: =G23+G24 -> -115818.17 | H25: =H23+H24 -> -144880.94 | I25: =I23+I24 -> -174737.19 | ... N25: =N23+N24 -> -340707.28 | O25: =N25 -> -340707.28
A27: CASH RUNWAY ANALYSIS
A28: Monthly Cash Burn / Generation | B28: =B21 -> 40000 | C28: =C21 -> -42943.333 | D28: =D21 -> -30278.866 | E28: =E21 -> -27051.481 | F28: =F21 -> -27133.857 | G28: =G21 -> -28410.628 | H28: =H21 -> -29062.77 | I28: =I21 -> -29856.254 | ... N28: =N21 -> -36059.223 | O28: =N25 -> -340707.28
A29: Cumulative Cash Burn | B29: =B28 -> 40000 | C29: =B29+C28 -> -2943.3333 | D29: =C29+D28 -> -33222.199 | E29: =D29+E28 -> -60273.68 | F29: =E29+F28 -> -87407.537 | G29: =F29+G28 -> -115818.17 | H29: =G29+H28 -> -144880.94 | I29: =H29+I28 -> -174737.19 | J29: =I29+J28 -> -205465 | ... N29: =M29+N28 -> -340707.28 | O29: =N29 -> -340707.28
A30: Months of Runway Remaining | B30: =IF(B28>=0,"N/A",IF(B25<=0,0,ROUND(-B25/B28,1))) -> N/A | C30: =IF(C28>=0,"N/A",IF(C25<=0,0,ROUND(-C25/C28,1))) -> 0 | D30: =IF(D28>=0,"N/A",IF(D25<=0,0,ROUND(-D25/D28,1))) -> 0 | E30: =IF(E28>=0,"N/A",IF(E25<=0,0,ROUND(-E25/E28,1))) -> 0 | F30: =IF(F28>=0,"N/A",IF(F25<=0,0,ROUND(-F25/F28,1))) -> 0 | G30: =IF(G28>=0,"N/A",IF(G25<=0,0,ROUND(-G25/G28,1))) -> 0 | H30: =IF(H28>=0,"N/A",IF(H25<=0,0,ROUND(-H25/H28,1))) -> 0 | I30: =IF(I28>=0,"N/A",IF(I25<=0,0,ROUND(-I25/I28,1))) -> 0 | ... N30: =IF(N28>=0,"N/A",IF(N25<=0,0,ROUND(-N25/N28,1))) -> 0
A32: KEY CASH METRICS
A33: Metric | B33: Value | D33: Metric | E33: Value
A34: Pre-Launch Capital | B34: =Assumptions!B109 -> 190000 | D34: Year 1 Total Revenue (Cash In) | E34: =O7 -> 143881.25
A35: Year 1 Closing Cash Balance | B35: =N25 -> -340707.28 | D35: Year 1 Total Outflows | E35: =O19 -> 674588.53
A36: Peak Monthly Burn | B36: =MIN(C28:N28) -> -42943.333 | D36: Avg Monthly Burn (M1-M12) | E36: =AVERAGE(C28:N28) -> -31725.607
A38: Additional Funding Required | B38: =IF(N25<0,ABS(N25),0) -> 340707.28 | D38: Recommended Raise (Burn + 30% Buffer) | E38: =ROUND(B38*1.3,-3) -> 443000
A39: Recommended Raise (USD) | B39: =E38*Assumptions!$B$15 -> 624630 | D39: Runway After Raise (months) | E39: =ROUND(E38/ABS(E36),1) -> 14
A42: 5-YEAR CASH FLOW PROJECTION
A43: All figures in Jordanian Dinars (JOD) | Year 1 from Monthly P&L, Years 2-5 from Multi-Year Projections
A45: Line Item | B45: Year 1 | C45: Year 2 | D45: Year 3 | E45: Year 4 | F45: Year 5 | G45: 5-Yr Total
A46: CASH INFLOWS
A47: Seed Capital / Investment | B47: =Assumptions!B109 -> 190000 | C47: 0 | D47: 0 | E47: 0 | F47: 0 | G47: =SUM(B47:F47) -> 190000
A48: Subscription Revenue | B48: ='Multi-Year Projections'!B21 -> 143881.25 | C48: ='Multi-Year Projections'!C21 -> 816763.5 | D48: ='Multi-Year Projections'!D21 -> 1712220.7 | E48: ='Multi-Year Projections'!E21 -> 3034126.5 | F48: ='Multi-Year Projections'!F21 -> 4711707.1 | G48: =SUM(B48:F48) -> 10418699
A49: Ancillary Revenue | B49: ='Multi-Year Projections'!B22 -> 0 | C49: ='Multi-Year Projections'!C22 -> 24120 | D49: ='Multi-Year Projections'!D22 -> 118140 | E49: ='Multi-Year Projections'!E22 -> 358884 | F49: ='Multi-Year Projections'!F22 -> 841680 | G49: =SUM(B49:F49) -> 1342824
A50: Total Cash Inflows | B50: =SUM(B47:B49) -> 333881.25 | C50: =SUM(C47:C49) -> 840883.5 | D50: =SUM(D47:D49) -> 1830360.7 | E50: =SUM(E47:E49) -> 3393010.5 | F50: =SUM(F47:F49) -> 5553387.1 | G50: =SUM(B50:F50) -> 11951523
A52: CASH OUTFLOWS
A53: Pre-Launch CapEx | B53: =Assumptions!B109 -> 190000 | C53: 0 | D53: 0 | E53: 0 | F53: 0 | G53: =SUM(B53:F53) -> 190000
A54: Cost of Revenue | B54: ='Multi-Year Projections'!B32 -> 124351.4 | C54: ='Multi-Year Projections'!C32 -> 295724.28 | D54: ='Multi-Year Projections'!D32 -> 546429.19 | E54: ='Multi-Year Projections'!E32 -> 885066.41 | F54: ='Multi-Year Projections'!F32 -> 1297444.6 | G54: =SUM(B54:F54) -> 3149015.8
A55: Operating Expenses | B55: ='Multi-Year Projections'!B45 -> 729140 | C55: ='Multi-Year Projections'!C45 -> 473941 | D55: ='Multi-Year Projections'!D45 -> 568729 | E55: ='Multi-Year Projections'!E45 -> 654038 | F55: ='Multi-Year Projections'!F45 -> 719441 | G55: =SUM(B55:F55) -> 3145289
A56: Depreciation & Amortization | B56: ='Multi-Year Projections'!B50 -> 11666.667 | C56: ='Multi-Year Projections'!C50 -> 13417 | D56: ='Multi-Year Projections'!D50 -> 14759 | E56: ='Multi-Year Projections'!E50 -> 15940 | F56: ='Multi-Year Projections'!F50 -> 16737 | G56: =SUM(B56:F56) -> 72519.667
A57: Interest Expense | B57: ='Multi-Year Projections'!B51 -> 0 | C57: ='Multi-Year Projections'!C51 -> 0 | D57: ='Multi-Year Projections'!D51 -> 0 | E57: ='Multi-Year Projections'!E51 -> 0 | F57: ='Multi-Year Projections'!F51 -> 0 | G57: =SUM(B57:F57) -> 0
A58: Total Cash Outflows | B58: =SUM(B53:B57) -> 1055158.1 | C58: =SUM(C53:C57) -> 783082.28 | D58: =SUM(D53:D57) -> 1129917.2 | E58: =SUM(E53:E57) -> 1555044.4 | F58: =SUM(F53:F57) -> 2033622.6 | G58: =SUM(B58:F58) -> 6556824.5
A60: NET CASH FLOW | B60: =B50-B58 -> -721276.82 | C60: =C50-C58 -> 57801.223 | D60: =D50-D58 -> 700443.55 | E60: =E50-E58 -> 1837966 | F60: =F50-F58 -> 3519764.6 | G60: =SUM(B60:F60) -> 5394698.6
A62: Opening Cash Balance | B62: 0 | C62: =B64 -> -721276.82 | D62: =C64 -> -663475.6 | E62: =D64 -> 36967.957 | F62: =E64 -> 1874934
A63: Net Cash Flow | B63: =B60 -> -721276.82 | C63: =C60 -> 57801.223 | D63: =D60 -> 700443.55 | E63: =E60 -> 1837966 | F63: =F60 -> 3519764.6
A64: CLOSING CASH BALANCE | B64: =B62+B63 -> -721276.82 | C64: =C62+C63 -> -663475.6 | D64: =D62+D63 -> 36967.957 | E64: =E62+E63 -> 1874934 | F64: =F62+F63 -> 5394698.6 | G64: =F64 -> 5394698.6
A66: Free Cash Flow (EBITDA - CapEx) | B66: ='Multi-Year Projections'!B47-B53 -> -899610.15 | C66: ='Multi-Year Projections'!C47 -> 71218.223 | D66: ='Multi-Year Projections'!D47 -> 715202.55 | E66: ='Multi-Year Projections'!E47 -> 1853906 | F66: ='Multi-Year Projections'!F47 -> 3536501.6 | G66: =SUM(B66:F66) -> 5277218.2
A67: FCF Margin % | B67: =IF(B50=0,0,B66/B50) -> -2.6944015 | C67: =IF(C50=0,0,C66/C50) -> 0.084694519 | D67: =IF(D50=0,0,D66/D50) -> 0.39074404 | E67: =IF(E50=0,0,E66/E50) -> 0.54638972 | F67: =IF(F50=0,0,F66/F50) -> 0.63681884
A68: Cash Positive Year | B68: =IF(B64>0,"Year 1",IF(C64>0,"Year 2",IF(D64>0,"Year 3",IF(E64>0,"Year 4",IF(F64>0,"Year 5","Beyond Y5"))))) -> Year 3

Sheet Stress Tests
A1: WASEL — STRESS TESTS & SENSITIVITY ANALYSIS
A2: Impact analysis on Year 1 financials under adverse scenarios | Updated for 3-tier cohort model
A4: SCENARIO 1: TRANSITION CHURN SENSITIVITY
A5: Metric | B5: Base Case | C5: M0→50% churn | D5: M0→50%, M2+ 10% | E5: All churn 2x | F5: Notes
A6: M0→M1 Churn | B6: 0.25 | C6: 0.5 | D6: 0.5 | E6: 0.6 | F6: First payment wall is #1 risk
A7: M2+ Ongoing Churn | B7: 0.04 | C7: 0.05 | D7: 0.1 | E7: 0.1 | F7: Higher ongoing attrition
A8: Est. EoY Active Drivers | B8: ='Monthly P&L'!N11 -> 1256 | C8: 750 | D8: 500 | E8: 350 | F8: Churn is the #1 risk to the model
A9: Assessment | B9: Planned | C9: Manageable | D9: Concerning | E9: Critical | F9: Low pricing mitigates churn pressure
A11: SCENARIO 2: COMBINED DOWNSIDE STRESS TEST
A12: Stress Factor | B12: Base Case | C12: Downside | D12: Impact
A13: M0→M1 retention | B13: 75% survive | C13: 50% survive | D13: ~30% fewer drivers reach full pricing
A14: M2+ ongoing churn | B14: 4%/mo | C14: 10%/mo | D14: Active driver pool shrinks faster
A15: Mandatory insurance increase | B15: JD 8.65/driver/mo | C15: JD 20/driver/mo | D15: ~JD 120K additional cost/yr at scale
A16: Avg trips per driver per day | B16: 9 trips/day | C16: 5 trips/day | D16: Reduces driver income → may increase churn
A18: Combined Impact | B18: Base Case (Y1) | C18: All-Downside (Y1) | D18: Δ Change
A19: End-of-Year Active Drivers | B19: ='Monthly P&L'!N11 -> 1256 | C19: 350 | D19: =(C19-B19)/B19 -> -0.72133758
A20: Annual Revenue (JOD) | B20: ='Monthly P&L'!O23 -> 143881.25 | C20: 45000 | D20: =(C20-B20)/B20 -> -0.68724208
A21: Annual Net Income (JOD) | B21: ='Monthly P&L'!O53 -> -392373.95 | C21: -500000 | D21: =(C21-B21)/B21 -> 0.2742946
A22: Assessment | B22: Losses expected Y1; funded by seed | C22: CRITICAL: Requires bridge funding
A24: SCENARIO 3: SUBSCRIPTION FEE SENSITIVITY (BLENDED M2+ FEE)
A25: Metric | B25: JD 22/mo | C25: JD 27/mo | D25: JD 32.25 (Base) | E25: JD 38/mo | F25: JD 45/mo | G25: Notes
A26: Blended Monthly Fee (JOD) | B26: 22 | C26: 27 | D26: =Assumptions!B50 -> 32.25 | E26: 38 | F26: 45
A27: Est. Annual Revenue (JOD) | B27: =ROUND(B20*(B26/D26),0) -> 98152 | C27: =ROUND(B20*(C26/D26),0) -> 120459 | D27: =B20 -> 143881.25 | E27: =ROUND(B20*(E26/D26),0) -> 169534 | F27: =ROUND(B20*(F26/D26),0) -> 200765
A28: vs Base Case Revenue | B28: =(B27-D27)/D27 -> -0.31782633 | C28: =(C27-D27)/D27 -> -0.16278876 | D28: BASE | E28: =(E27-D27)/D27 -> 0.17829113 | F28: =(F27-D27)/D27 -> 0.39535207
A29: Fee as % of Driver Gross (~JD 520/mo) | B29: =B26/Assumptions!$B$11 -> 0.03966966 | C29: =C26/Assumptions!$B$11 -> 0.048685492 | D29: =D26/Assumptions!$B$11 -> 0.058152115 | E29: =E26/Assumptions!$B$11 -> 0.068520322 | F29: =F26/Assumptions!$B$11 -> 0.081142486 | G29: vs 30% at Uber/Careem
A31: SCENARIO 4: BREAK-EVEN BY ACTIVE M2+ DRIVER COUNT
A32: Active M2+ Drivers | B32: Monthly Revenue | C32: Monthly COGS | D32: Monthly OPEX | E32: Monthly P&L | F32: Status
A33: 500 | B33: =A33*Assumptions!$B$50 -> 16125 | C33: =A33*Assumptions!$B$59+Assumptions!$B$63+Assumptions!$B$64+Assumptions!$B$65 -> 5725 | D33: =Assumptions!$C$87+Assumptions!$B$69+Assumptions!$C$98+Assumptions!$C$85 -> 21983.333 | E33: =B33-C33-D33 -> -11583.333 | F33: ❌ Loss
A34: 1000 | B34: =A34*Assumptions!$B$50 -> 32250 | C34: =A34*Assumptions!$B$59+Assumptions!$B$63+Assumptions!$B$64+Assumptions!$B$65 -> 10050 | D34: =Assumptions!$C$87+Assumptions!$B$69+Assumptions!$C$98+Assumptions!$C$85 -> 21983.333 | E34: =B34-C34-D34 -> 216.66667 | F34: ❌ Loss
A35: 1500 | B35: =A35*Assumptions!$B$50 -> 48375 | C35: =A35*Assumptions!$B$59+Assumptions!$B$63+Assumptions!$B$64+Assumptions!$B$65 -> 14375 | D35: =Assumptions!$C$87+Assumptions!$B$69+Assumptions!$C$98+Assumptions!$C$85 -> 21983.333 | E35: =B35-C35-D35 -> 12016.667 | F35: =IF(E35>=0,"✅ Profitable","❌ Loss") -> ✅ Profitable
A36: 2000 | B36: =A36*Assumptions!$B$50 -> 64500 | C36: =A36*Assumptions!$B$59+Assumptions!$B$63+Assumptions!$B$64+Assumptions!$B$65 -> 18700 | D36: =Assumptions!$C$87+Assumptions!$B$69+Assumptions!$C$98+Assumptions!$C$85 -> 21983.333 | E36: =B36-C36-D36 -> 23816.667 | F36: =IF(E36>=0,"✅ Profitable","❌ Loss") -> ✅ Profitable
A37: 3000 | B37: =A37*Assumptions!$B$50 -> 96750 | C37: =A37*Assumptions!$B$59+Assumptions!$B$63+Assumptions!$B$64+Assumptions!$B$65 -> 27350 | D37: =Assumptions!$C$87+Assumptions!$B$69+Assumptions!$C$98+Assumptions!$C$85 -> 21983.333 | E37: =B37-C37-D37 -> 47416.667 | F37: =IF(E37>=0,"✅ Profitable","❌ Loss") -> ✅ Profitable
A38: 5000 | B38: =A38*Assumptions!$B$50 -> 161250 | C38: =A38*Assumptions!$B$59+Assumptions!$B$63+Assumptions!$B$64+Assumptions!$B$65 -> 44650 | D38: =Assumptions!$C$87+Assumptions!$B$69+Assumptions!$C$98+Assumptions!$C$85 -> 21983.333 | E38: =B38-C38-D38 -> 94616.667 | F38: =IF(E38>=0,"✅ Profitable","❌ Loss") -> ✅ Profitable
A40: Break-even requires ~1,200 active M2+ drivers paying full tier pricing (excl. M0/M1 onboarding drivers)
A42: SCENARIO 5: UNIT ECONOMICS SENSITIVITY (INVESTOR STRESS TEST)
A43: What happens to LTV/CAC when churn assumptions worsen?
A44: Mature Churn Rate (M6+) | B44: Avg Lifespan (Mo) | C44: LTV (JOD) | D44: LTV/CAC | E44: Survives? | F44: Assessment
A45: 0.025 | B45: 27 | C45: =B45*'Unit Economics'!$B$44 -> 476.85712 | D45: =C45/'Unit Economics'!$B$53 -> 10.596825 | E45: ✅ Yes — LTV/CAC >3x | F45: ✅ Base case — strong
A46: 0.05 | B46: 16 | C46: =B46*'Unit Economics'!$B$44 -> 282.582 | D46: =C46/'Unit Economics'!$B$53 -> 6.2796 | E46: ✅ Yes — LTV/CAC >3x | F46: ✅ Still healthy (>3x)
A47: 0.075 | B47: 11 | C47: =B47*'Unit Economics'!$B$44 -> 194.27513 | D47: =C47/'Unit Economics'!$B$53 -> 4.317225 | E47: ✅ Yes — LTV/CAC >3x | F47: ✅ Acceptable
A48: 0.1 | B48: 8 | C48: =B48*'Unit Economics'!$B$44 -> 141.291 | D48: =C48/'Unit Economics'!$B$53 -> 3.1398 | E48: ⚠️ Borderline at 3.7x | F48: ⚠️ Marginal — review spending
A49: 0.15 | B49: 5.5 | C49: =B49*'Unit Economics'!$B$44 -> 97.137563 | D49: =C49/'Unit Economics'!$B$53 -> 2.1586125 | E49: ❌ No — LTV/CAC <3x | F49: ❌ Unit economics break down
A50: Takeaway: Model survives up to ~10% mature churn before LTV/CAC drops below 3x threshold.
A52: SCENARIO 6: FUNDING GAP & RUNWAY ANALYSIS
A53: How much capital is really needed, and when does the model require it?
A54: Metric | B54: Amount (JOD) | C54: Amount (USD) | D54: Notes
A55: Pre-Launch Capital (Seed) | B55: =Assumptions!B109 -> 190000 | C55: =B55*Assumptions!$B$15 -> 267900 | D55: Covers MVP, license, bank guarantee, marketing
A56: Year 1 Operating Cash Burn | B56: ='Monthly P&L'!O53 -> -392373.95 | C56: =B56*Assumptions!$B$15 -> -553247.26 | D56: Revenue ramp cannot cover OPEX + regulatory in Y1
A57: Total Y1 Capital Required | B57: =ABS(B56)+B55 -> 582373.95 | C57: =B57*Assumptions!$B$15 -> 821147.26 | D57: Total: pre-launch + operating burn
A58: Funding Gap (Seed - Required) | B58: =B55-B57 -> -392373.95 | C58: =B58*Assumptions!$B$15 -> -553247.26 | D58: Additional capital needed beyond seed
A59: Recommended Raise (with 30% buffer) | B59: =ROUND(ABS(B58)*1.3,-3) -> 510000 | C59: =B59*Assumptions!$B$15 -> 719100 | D59: Bridge/Series A to reach profitability
A60: Est. Months of Runway (post-raise) | B60: =ROUND((B55+B59)/ABS('Cash Flow'!N18),1) -> 16.5 | C60: months | D60: Based on peak monthly burn rate
A62: SCENARIO 7: JORDAN MARKET REALITY CHECK
A63: Key assumptions benchmarked against Jordan ride-hailing market data
A64: Assumption | B64: Model Value | C64: Jordan Benchmark | D64: Risk Level | E64: Investor Note
A65: Avg fare per trip | B65: JD 2.50 | C65: JD 2-3 (Amman taxis) | D65: ✅ Low | E65: Well within observed range
A66: Driver trips/day | B66: 9 (blended) | C66: 6-10 (Uber/Careem Amman) | D66: ✅ Low | E66: Conservative blended estimate
A67: Cash payment % | B67: 0.65 | C67: 60-70% (JCB 2024) | D67: ✅ Low | E67: Aligned with Jordan's cash economy
A68: Monthly driver growth | B68: 30% MoM | C68: 15-25% (MENA startups); 30% justified by validated driver pain point | D68: ✅ Validated | E68: Driver community validation; solving real social pain (30% commission vs flat fee)
A69: Mature churn (M6+) | B69: 2%/mo | C69: 3-5% (subscription apps MENA) | D69: ✅ Low | E69: Conservative; insurance lock-in supports retention

Sheet Multi-Year Projections
A1: WASEL — 5-YEAR FINANCIAL PROJECTIONS
A2: All figures in Jordanian Dinars (JOD) | USD equivalent at 1 JOD = $1.41 | Cohort model
A4: Line Item | B4: Year 1 | C4: Year 2 | D4: Year 3 | E4: Year 4 | F4: Year 5 | G4: 5-Yr CAGR | H4: 5-Yr Total
A5: GROWTH ASSUMPTIONS
A6: Annual Net Driver Growth Rate | B6: N/A | C6: 1.2 | D6: 0.85 | E6: 0.6 | F6: 0.45
A7: Blended Fee Growth (Tier Mix Shift) | B7: N/A | C7: 0.05 | D7: 0.07 | E7: 0.05 | F7: 0.03
A8: Fixed OPEX Growth Rate | B8: N/A | C8: 0.3 | D8: 0.2 | E8: 0.15 | F8: 0.1
A9: Cities Operating | B9: 1 | C9: 3 | D9: 4 | E9: 6 | F9: 8
A10: Ancillary Revenue / Driver / Mo (JOD) | B10: 0 | C10: 1 | D10: 2.5 | E10: 4.5 | F10: 7
A13: KEY OPERATING METRICS
A14: Active Drivers (End of Year) | B14: ='Monthly P&L'!N11 -> 1256 | C14: =ROUND(B14*(1+C6),0) -> 2763 | D14: =ROUND(C14*(1+D6),0) -> 5112 | E14: =ROUND(D14*(1+E6),0) -> 8179 | F14: =ROUND(E14*(1+F6),0) -> 11860 | G14: =(F14/B14)^(1/4)-1 -> 0.75296709
A15: Avg Active Drivers (Annual) | B15: ='Monthly P&L'!O6/2 -> 958 | C15: =ROUND((B14+C14)/2,0) -> 2010 | D15: =ROUND((C14+D14)/2,0) -> 3938 | E15: =ROUND((D14+E14)/2,0) -> 6646 | F15: =ROUND((E14+F14)/2,0) -> 10020
A16: Blended Monthly Fee / Driver (JOD) | B16: =Assumptions!B50 -> 32.25 | C16: =B16*(1+C7) -> 33.8625 | D16: =C16*(1+D7) -> 36.232875 | E16: =D16*(1+E7) -> 38.044519 | F16: =E16*(1+F7) -> 39.185854
A17: Team Headcount | B17: 5 | C17: 9 | D17: 15 | E17: 22 | F17: 30
A20: REVENUE
A21: Subscription Revenue | B21: ='Monthly P&L'!O23 -> 143881.25 | C21: =C15*C16*12 -> 816763.5 | D21: =D15*D16*12 -> 1712220.7 | E21: =E15*E16*12 -> 3034126.5 | F21: =F15*F16*12 -> 4711707.1 | H21: =SUM(B21:F21) -> 10418699
A22: Ancillary Revenue (Ads, Data, Partnerships) | B22: 0 | C22: =C15*C10*12 -> 24120 | D22: =D15*D10*12 -> 118140 | E22: =E15*E10*12 -> 358884 | F22: =F15*F10*12 -> 841680 | H22: =SUM(B22:F22) -> 1342824
A23: TOTAL REVENUE | B23: =B21+B22 -> 143881.25 | C23: =C21+C22 -> 840883.5 | D23: =D21+D22 -> 1830360.7 | E23: =E21+E22 -> 3393010.5 | F23: =F21+F22 -> 5553387.1 | G23: =(F23/B23)^(1/4)-1 -> 1.4925188 | H23: =SUM(B23:F23) -> 11761523
A24: YoY Revenue Growth | B24: N/A | C24: =(C23-B23)/B23 -> 4.8442883 | D24: =(D23-C23)/C23 -> 1.1767114 | E24: =(E23-D23)/D23 -> 0.85373866 | F24: =(F23-E23)/E23 -> 0.63671382
A27: COST OF REVENUE
A28: Payment Processing Fees | B28: ='Monthly P&L'!O26 -> 1510.7531 | C28: =C23*Assumptions!$B$13*Assumptions!$B$14 -> 8829.2768 | D28: =D23*Assumptions!$B$13*Assumptions!$B$14 -> 19218.788 | E28: =E23*Assumptions!$B$13*Assumptions!$B$14 -> 35626.61 | F28: =F23*Assumptions!$B$13*Assumptions!$B$14 -> 58310.565 | H28: =SUM(B28:F28) -> 123495.99
A29: Insurance Program Costs | B29: ='Monthly P&L'!O27 -> 62409.75 | C29: =C15*Assumptions!$B$59*12 -> 208638 | D29: =D15*Assumptions!$B$59*12 -> 408764.4 | E29: =E15*Assumptions!$B$59*12 -> 689854.8 | F29: =F15*Assumptions!$B$59*12 -> 1040076 | H29: =SUM(B29:F29) -> 2409743
A30: Cloud & Tech Infrastructure | B30: ='Monthly P&L'!O28+'Monthly P&L'!O29+'Monthly P&L'!O30 -> 31690.9 | C30: =ROUND(B30*(C15/B15)^0.6,0) -> 49435 | D30: =ROUND(C30*(D15/C15)^0.6,0) -> 74009 | E30: =ROUND(D30*(E15/D15)^0.6,0) -> 101311 | F30: =ROUND(E30*(F15/E15)^0.6,0) -> 129611 | H30: =SUM(B30:F30) -> 386056.9
A31: Driver Onboarding & Verification | B31: ='Monthly P&L'!O31 -> 28740 | C31: =ROUND((C14-B14+C14*0.15)*Assumptions!$B$67,0) -> 28822 | D31: =ROUND((D14-C14+D14*0.12)*Assumptions!$B$67,0) -> 44437 | E31: =ROUND((E14-D14+E14*0.1)*Assumptions!$B$67,0) -> 58274 | F31: =ROUND((F14-E14+F14*0.08)*Assumptions!$B$67,0) -> 69447 | H31: =SUM(B31:F31) -> 229720
A32: Total Cost of Revenue | B32: =SUM(B28:B31) -> 124351.4 | C32: =SUM(C28:C31) -> 295724.28 | D32: =SUM(D28:D31) -> 546429.19 | E32: =SUM(E28:E31) -> 885066.41 | F32: =SUM(F28:F31) -> 1297444.6 | H32: =SUM(B32:F32) -> 3149015.8
A34: GROSS PROFIT | B34: =B23-B32 -> 19529.847 | C34: =C23-C32 -> 545159.22 | D34: =D23-D32 -> 1283931.6 | E34: =E23-E32 -> 2507944 | F34: =F23-F32 -> 4255942.6 | H34: =SUM(B34:F34) -> 8612507.2
A35: Gross Margin % | B35: =IF(B23=0,0,B34/B23) -> 0.13573587 | C35: =IF(C23=0,0,C34/C23) -> 0.64831718 | D35: =IF(D23=0,0,D34/D23) -> 0.70146366 | E35: =IF(E23=0,0,E34/E23) -> 0.73915011 | F35: =IF(F23=0,0,F34/F23) -> 0.76636879
A37: OPERATING EXPENSES
A38: Team & Overhead (Salaries + Office) | B38: ='Monthly P&L'!O38 -> 90000 | C38: =ROUND(B38*1.3,0) -> 117000 | D38: =ROUND(C38*1.2,0) -> 140400 | E38: =ROUND(D38*1.15,0) -> 161460 | F38: =ROUND(E38*1.1,0) -> 177606 | H38: =SUM(B38:F38) -> 686466
A39: Customer Support | B39: ='Monthly P&L'!O39 -> 43290 | C39: =ROUND(B39*1.3,0) -> 56277 | D39: =ROUND(C39*1.2,0) -> 67532 | E39: =ROUND(D39*1.15,0) -> 77662 | F39: =ROUND(E39*1.1,0) -> 85428 | H39: =SUM(B39:F39) -> 330189
A40: Marketing — Driver Acquisition | B40: ='Monthly P&L'!O40 -> 57480 | C40: =ROUND(B40*1.3,0) -> 74724 | D40: =ROUND(C40*1.2,0) -> 89669 | E40: =ROUND(D40*1.15,0) -> 103119 | F40: =ROUND(E40*1.1,0) -> 113431 | H40: =SUM(B40:F40) -> 438423
A41: Rider Acquisition & Promos | B41: ='Monthly P&L'!O41 -> 36000 | C41: =ROUND(B41*1.3,0) -> 46800 | D41: =ROUND(C41*1.2,0) -> 56160 | E41: =ROUND(D41*1.15,0) -> 64584 | F41: =ROUND(E41*1.1,0) -> 71042 | H41: =SUM(B41:F41) -> 274586
A42: Regulatory & LTRC License Fee | B42: ='Monthly P&L'!O42 -> 133000 | C42: =ROUND(B42*1.3,0) -> 172900 | D42: =ROUND(C42*1.2,0) -> 207480 | E42: =ROUND(D42*1.15,0) -> 238602 | F42: =ROUND(E42*1.1,0) -> 262462 | H42: =SUM(B42:F42) -> 1014444
A43: Legal & Accounting | B43: ='Monthly P&L'!O43 -> 4800 | C43: =ROUND(B43*1.3,0) -> 6240 | D43: =ROUND(C43*1.2,0) -> 7488 | E43: =ROUND(D43*1.15,0) -> 8611 | F43: =ROUND(E43*1.1,0) -> 9472 | H43: =SUM(B43:F43) -> 36611
A44: OPEX Variance Adjustment (Y1 only) | B44: ='Monthly P&L'!O45-'Monthly P&L'!O44 -> 364570 | C44: 0 | D44: 0 | E44: 0 | F44: 0 | H44: =SUM(B44:F44) -> 364570
A45: Total Operating Expenses | B45: =SUM(B38:B44) -> 729140 | C45: =SUM(C38:C44) -> 473941 | D45: =SUM(D38:D44) -> 568729 | E45: =SUM(E38:E44) -> 654038 | F45: =SUM(F38:F44) -> 719441 | H45: =SUM(B45:F45) -> 3145289
A47: EBITDA | B47: =B34-B45 -> -709610.15 | C47: =C34-C45 -> 71218.223 | D47: =D34-D45 -> 715202.55 | E47: =E34-E45 -> 1853906 | F47: =F34-F45 -> 3536501.6 | H47: =SUM(B47:F47) -> 5467218.2
A48: EBITDA Margin % | B48: =IF(B23=0,0,B47/B23) -> -4.9319154 | C48: =IF(C23=0,0,C47/C23) -> 0.084694519 | D48: =IF(D23=0,0,D47/D23) -> 0.39074404 | E48: =IF(E23=0,0,E47/E23) -> 0.54638972 | F48: =IF(F23=0,0,F47/F23) -> 0.63681884
A50: Depreciation & Amortization | B50: ='Monthly P&L'!O50 -> 11666.667 | C50: =ROUND(B50*1.15,0) -> 13417 | D50: =ROUND(C50*1.1,0) -> 14759 | E50: =ROUND(D50*1.08,0) -> 15940 | F50: =ROUND(E50*1.05,0) -> 16737 | H50: =SUM(B50:F50) -> 72519.667
A51: Interest Expense | B51: ='Monthly P&L'!O51 -> 0 | C51: =ROUND(B51*0.85,0) -> 0 | D51: =ROUND(C51*0.7,0) -> 0 | E51: =ROUND(D51*0.5,0) -> 0 | F51: =ROUND(E51*0.3,0) -> 0 | H51: =SUM(B51:F51) -> 0
A53: NET INCOME | B53: =B47-B50-B51 -> -721276.82 | C53: =C47-C50-C51 -> 57801.223 | D53: =D47-D50-D51 -> 700443.55 | E53: =E47-E50-E51 -> 1837966 | F53: =F47-F50-F51 -> 3519764.6 | H53: =SUM(B53:F53) -> 5394698.6
A54: Net Margin % | B54: =IF(B23=0,0,B53/B23) -> -5.0130008 | C54: =IF(C23=0,0,C53/C23) -> 0.068738682 | D54: =IF(D23=0,0,D53/D23) -> 0.3826806 | E54: =IF(E23=0,0,E53/E23) -> 0.54169183 | F54: =IF(F23=0,0,F53/F23) -> 0.63380501
A55: Cumulative Net Income | B55: =B53 -> -721276.82 | C55: =B55+C53 -> -663475.6 | D55: =C55+D53 -> 36967.957 | E55: =D55+E53 -> 1874934 | F55: =E55+F53 -> 5394698.6 | H55: =F55 -> 5394698.6
A57: KEY METRICS & RATIOS
A58: Revenue per Driver (Annual) | B58: =IF(B15=0,0,B23/B15) -> 150.1892 | C58: =IF(C15=0,0,C23/C15) -> 418.35 | D58: =IF(D15=0,0,D23/D15) -> 464.7945 | E58: =IF(E15=0,0,E23/E15) -> 510.53423 | F58: =IF(F15=0,0,F23/F15) -> 554.23025
A59: COGS as % of Revenue | B59: =IF(B23=0,0,B32/B23) -> 0.86426413 | C59: =IF(C23=0,0,C32/C23) -> 0.35168282 | D59: =IF(D23=0,0,D32/D23) -> 0.29853634 | E59: =IF(E23=0,0,E32/E23) -> 0.26084989 | F59: =IF(F23=0,0,F32/F23) -> 0.23363121
A60: OPEX as % of Revenue | B60: =IF(B23=0,0,B45/B23) -> 5.0676513 | C60: =IF(C23=0,0,C45/C23) -> 0.56362267 | D60: =IF(D23=0,0,D45/D23) -> 0.31071962 | E60: =IF(E23=0,0,E45/E23) -> 0.19276038 | F60: =IF(F23=0,0,F45/F23) -> 0.12954995
A61: YoY Revenue Growth % | B61: — | C61: =(C23-B23)/B23 -> 4.8442883 | D61: =(D23-C23)/C23 -> 1.1767114 | E61: =(E23-D23)/D23 -> 0.85373866 | F61: =(F23-E23)/E23 -> 0.63671382
A62: Break-Even Year | B62: =IF(B53>0,"Year 1",IF(C53>0,"Year 2",IF(D53>0,"Year 3",IF(E53>0,"Year 4",IF(F53>0,"Year 5","Beyond Y5"))))) -> Year 2
A63: Cumulative Payback Year | B63: =IF(B55>0,"Year 1",IF(C55>0,"Year 2",IF(D55>0,"Year 3",IF(E55>0,"Year 4",IF(F55>0,"Year 5","Beyond Y5"))))) -> Year 3
A65: 5-YEAR TOTALS
A66: Total Revenue (5Y) | B66: =H23 -> 11761523
A67: Total Net Income (5Y) | B67: =H53 -> 5394698.6
A68: 5Y Revenue CAGR | B68: =(F23/B23)^(1/4)-1 -> 1.4925188
A71: STRATEGIC GROWTH LEVERS — HOW TO RAISE NUMBERS
A73: GAP ANALYSIS | B73: Current Path | C73: Target | D73: Gap | E73: Solution
A74: Year 5 Active Drivers | B74: =F15 -> 10020 | C74: 23000 | D74: =C74-B74 -> 12980 | E74: Jordan multi-city Y1 + Iraq/Egypt Y2-Y3 expansion
A75: Year 1 Revenue | B75: =B23 -> 143881.25 | C75: 533613 | D75: =C75-B75 -> 389731.75 | E75: Faster onboarding: 2-week M0 + referral incentives
A76: Year 5 Revenue | B76: =F23 -> 5553387.1 | C76: 8000000 | D76: =C76-B76 -> 2446612.9 | E76: Regional expansion + ancillary revenue + tier upsell
A78: RECOMMENDED GROWTH INITIATIVES | B78: Impact | C78: Timeline | D78: Effort | E78: Revenue Uplift Est.
A79: 1. Multi-City Jordan Expansion (Irbid, Zarqa, Aqaba in Y1) | B79: HIGH | C79: Y1-Y2 | D79: High | E79: +JD 2-4M/yr by Y5
A80: → Jordan cities add 2,000-3,000 drivers; validates model before regional expansion
A81: 2. Accelerated Onboarding (2-week M0 instead of 1 month) | B81: MEDIUM | C81: Y1-Q2 | D81: Low | E81: +JD 80-120K/yr Y1
A82: → Faster transition to paid tiers = higher Y1 revenue
A83: 3. Tier Upsell Program (Shift mix to 35%/40%/25%) | B83: MEDIUM | C83: Y2+ | D83: Medium | E83: +JD 3-5 ARPU/mo
A84: → Blended fee rises from JD 32.25 to ~JD 36.50
A85: 4. Ancillary Revenue Streams (Delivery, Corporate, Ads) | B85: HIGH | C85: Y2-Y3 | D85: High | E85: +JD 500K-1.5M/yr by Y4
A86: → Detailed in Future Revenue Streams tab (Phase 7)
A87: 5. Referral Bonuses & Driver Incentives | B87: HIGH | C87: Y1-Q1 | D87: Low | E87: +30-50% driver growth rate

Sheet Executive Summary
A1: WASEL — EXECUTIVE SUMMARY
A2: Subscription-Based Ride-Hailing Platform | Amman, Jordan | 3-Tier Model with Graduated Onboarding
A4: COMPANY OVERVIEW
A6: Wasel is a subscription-based ride-hailing platform launching in Amman, Jordan. Unlike Uber and Careem, which charge
A7: drivers a 30% commission per ride, Wasel charges a low flat monthly subscription fee and lets drivers keep 100% of their
A8: fares. Drivers enter through a graduated onboarding program (free trial → ramp → full tier) to reduce friction and churn.
A10: MARKET OPPORTUNITY
A11: Metric | B11: Value | D11: Metric | E11: Value
A12: Target City | B12: Amman (4.5M metro) | D12: Jordan Ride-Hailing Market (2025) | E12: $61.5M
A13: Estimated Addressable Drivers | B13: =Assumptions!B30 -> 25000 | D13: Market Growth Rate (CAGR) | E13: 0.052
A14: Seed Drivers (Month 1) | B14: =Assumptions!B28 -> 250 | D14: Competitors | E14: Uber, Careem, Jeeny
A16: 3-TIER SUBSCRIPTION MODEL
A17: Tier | B17: Monthly Fee (JOD) | C17: Fee (USD) | D17: Trips/Day Cap | E17: Driver Mix | F17: Sub as % of Gross | G17: Net Driver Income
A18: 🟢 Starter | B18: =Assumptions!B47 -> 20 | C18: =Assumptions!C47 -> 28.2 | D18: =Assumptions!E47 -> 8 | E18: =Assumptions!D47 -> 0.45 | F18: ='Tiered Plans'!B12 -> 0.040571243 | G18: ='Unit Economics'!B10 -> 122.96
A19: 🔵 Core | B19: =Assumptions!B48 -> 35 | C19: =Assumptions!C48 -> 49.35 | D19: =Assumptions!E48 -> 9 | E19: =Assumptions!D48 -> 0.35 | F19: ='Tiered Plans'!C12 -> 0.063110823 | G19: ='Unit Economics'!C10 -> 169.58
A20: 🟡 Pro | B20: =Assumptions!B49 -> 55 | C20: =Assumptions!C49 -> 77.55 | D20: =Assumptions!E49 -> 12 | E20: =Assumptions!D49 -> 0.2 | F20: ='Tiered Plans'!D12 -> 0.074380612 | G20: ='Unit Economics'!D10 -> 334.44
A21: Blended Average | B21: =Assumptions!B50 -> 32.25 | C21: =B21*Assumptions!$B$15 -> 45.4725 | D21: =Assumptions!B9 -> 9 | E21: 1 | G21: ='Unit Economics'!E10 -> 172.33
A23: Pricing Edge: A driver earning JD 520/month gross pays just JD 32.25 (6.2%) vs. Uber/Careem's 30% commission (JD 156). Drivers save JD 124/month — a 79% reduction.
A25: GRADUATED ONBOARDING PROGRAM
A26: Stage | B26: Duration | C26: Fee (JOD) | D26: Trips/Day Cap | E26: Churn at Transition | F26: Purpose
A27: M0 — Trial | B27: 1 month | C27: =Assumptions!C34 -> 0 | D27: =Assumptions!D34 -> 5 trips/day | E27: =Assumptions!B40 -> 0.25 | F27: Zero-risk trial to build trust
A28: M1 — Ramp | B28: 1 month | C28: =Assumptions!C35 -> 10 | D28: =Assumptions!D35 -> 7 trips/day | E28: =Assumptions!B41 -> 0.12 | F28: Low-cost transition to paid model
A29: M2+ — Full Tier | B29: Ongoing | C29: JD 20-55 | D29: Per tier | E29: =Assumptions!B42 -> 0.04 | F29: Full pricing, auto-assigned tier
A30: M6+ — Mature | B30: Ongoing | C30: JD 20-55 | D30: Per tier | E30: =Assumptions!B43 -> 0.02 | F30: Loyal drivers, lowest churn
A32: 5-YEAR FINANCIAL HIGHLIGHTS
A33: Metric | B33: Year 1 | C33: Year 2 | D33: Year 3 | E33: Year 4 | F33: Year 5
A34: Active Drivers (EoY) | B34: ='Multi-Year Projections'!B14 -> 1256 | C34: ='Multi-Year Projections'!C14 -> 2763 | D34: ='Multi-Year Projections'!D14 -> 5112 | E34: ='Multi-Year Projections'!E14 -> 8179 | F34: ='Multi-Year Projections'!F14 -> 11860
A35: Total Revenue (JOD) | B35: ='Multi-Year Projections'!B23 -> 143881.25 | C35: ='Multi-Year Projections'!C23 -> 840883.5 | D35: ='Multi-Year Projections'!D23 -> 1830360.7 | E35: ='Multi-Year Projections'!E23 -> 3393010.5 | F35: ='Multi-Year Projections'!F23 -> 5553387.1
A36: EBITDA (JOD) | B36: ='Multi-Year Projections'!B47 -> -709610.15 | C36: ='Multi-Year Projections'!C47 -> 71218.223 | D36: ='Multi-Year Projections'!D47 -> 715202.55 | E36: ='Multi-Year Projections'!E47 -> 1853906 | F36: ='Multi-Year Projections'!F47 -> 3536501.6
A37: Net Income (JOD) | B37: ='Multi-Year Projections'!B53 -> -721276.82 | C37: ='Multi-Year Projections'!C53 -> 57801.223 | D37: ='Multi-Year Projections'!D53 -> 700443.55 | E37: ='Multi-Year Projections'!E53 -> 1837966 | F37: ='Multi-Year Projections'!F53 -> 3519764.6
A38: EBITDA Margin % | B38: ='Multi-Year Projections'!B48 -> -4.9319154 | C38: ='Multi-Year Projections'!C48 -> 0.084694519 | D38: ='Multi-Year Projections'!D48 -> 0.39074404 | E38: ='Multi-Year Projections'!E48 -> 0.54638972 | F38: ='Multi-Year Projections'!F48 -> 0.63681884
A39: Cumulative Net Income (JOD) | B39: ='Multi-Year Projections'!B55 -> -721276.82 | C39: ='Multi-Year Projections'!C55 -> -663475.6 | D39: ='Multi-Year Projections'!D55 -> 36967.957 | E39: ='Multi-Year Projections'!E55 -> 1874934 | F39: ='Multi-Year Projections'!F55 -> 5394698.6
A41: UNIT ECONOMICS & INVESTOR SCORECARD
A42: Metric | B42: Value | C42: Benchmark | D42: Rating | F42: Metric | G42: Value
A43: LTV per Driver (JOD) | B43: ='Unit Economics'!B45 -> 627.58636 | C43: > JD 200 | D43: ✅ Excellent | F43: Break-Even Year | G43: ='Multi-Year Projections'!B62 -> Year 2
A44: CAC per Driver (JOD) | B44: ='Unit Economics'!B51 -> 30 | C44: < JD 50 | D44: ✅ Strong | F44: Cumulative Payback Year | G44: ='Multi-Year Projections'!B63 -> Year 3
A45: LTV / CAC Ratio | B45: ='Unit Economics'!B54 -> 13.946364 | C45: > 3x | D45: ✅ Excellent | F45: 5Y Revenue CAGR | G45: ='Multi-Year Projections'!B68 -> 1.4925188
A46: CAC Payback (months) | B46: ='Unit Economics'!B55 -> 2.547933 | C46: < 12 months | D46: ✅ Excellent | F46: 5Y Cumulative Net Income | G46: ='Multi-Year Projections'!B67 -> 5394698.6
A47: Contribution Margin / Driver | B47: ='Unit Economics'!E33 -> 17.661375 | C47: > JD 15 | D47: ✅ Strong | F47: Pre-Launch Capital (JOD) | G47: =Assumptions!B109 -> 190000
A49: FUNDING & CAPITAL REQUIREMENTS
A50: Item | B50: Amount (JOD) | C50: Amount (USD) | D50: Notes
A51: Pre-Launch Capital | B51: =Assumptions!B109 -> 190000 | C51: =B51*Assumptions!$B$15 -> 267900 | D51: Tech, legal, regulatory, initial marketing
A52: Year 1 Cash Burn (Net) | B52: ='Multi-Year Projections'!B53 -> -721276.82 | C52: =B52*Assumptions!$B$15 -> -1017000.3 | D52: Heaviest burn year (startup costs + ramp)
A53: Recommended Seed Round | B53: =ROUND(ABS(B52)*1.3,-3) -> 938000 | C53: =B53*Assumptions!$B$15 -> 1322580 | D53: Burn + 30% buffer for 18-month runway
A55: KEY RISKS & MITIGANTS
A56: Risk | B56: Severity | C56: Mitigant
A57: Regulatory delay (LTRC license) | B57: HIGH | C57: JD 158K regulatory budget; legal counsel engaged pre-launch
A58: Driver churn exceeds projections | B58: MEDIUM | C58: Graduated onboarding filters uncommitted; 2% mature churn with insurance lock-in
A59: Competitor price war (Uber/Careem) | B59: MEDIUM | C59: Wasel's flat fee is structurally cheaper; 79% savings vs commission model
A60: Slower driver adoption | B60: LOW | C60: Break-even at just 1,500 M2+ drivers (Stress Tests); referral program accelerates growth
A61: Single-city concentration | B61: LOW | C61: Jordan multi-city expansion Y1 (Irbid, Zarqa, Aqaba); Iraq/Egypt from Y2-Y3
A63: THE INVESTMENT THESIS
A65: ✅ Massive driver savings: JD 124/month vs. commission model (79% cheaper)
A66: ✅ Strong unit economics: LTV/CAC of 13.9x with 2.5-month payback
A67: ✅ Graduated onboarding reduces churn: 25% trial dropout filters to 2% mature churn
A68: ✅ Fast path to profitability: Net income positive by Year 2, cumulative payback by Year 3
A69: ✅ Scalable model: 152% revenue CAGR with JD 6.6M cumulative net income over 5 years
A70: ✅ Regional expansion: Amman → 3 Jordan cities Y1 → Iraq JV + Egypt Y2-Y3 → 8 markets by Y5
A72: For detailed projections, see: Assumptions | Tiered Plans | Monthly P&L | Unit Economics | Cash Flow | Stress Tests | Multi-Year Projections

Sheet Market Expansion
A1: WASEL — REGIONAL EXPANSION STRATEGY & PILOT PROJECTIONS
A2: Phased rollout across non-GCC Arab markets — where drivers need Wasel most
A4: EXPANSION ROADMAP OVERVIEW
A5: Market | B5: Population | C5: Est. Market Size | D5: Timeline | E5: Pilot Drivers | F5: Year 1, Q3 | G5: Priority
A6: Irbid, Jordan | B6: 2.1M | C6: $18M | D6: Year 2, Q1 | E6: 500 | F6: Year 1, Q4 | G6: 🔴 Critical
A7: Zarqa, Jordan | B7: 1.5M | C7: $12M | D7: Year 2, Q2 | E7: 400 | F7: Year 2, Q1 | G7: 🔴 Critical
A8: Aqaba, Jordan | B8: 0.2M | C8: $5M | D8: Year 2, Q3 | E8: 300 | F8: ✅ High | G8: 🟡 High
F9: Year 2, Q3
A10: Iraq (Baghdad, Erbil, Basra) | B10: 44M | C10: $120M+ | D10: Year 3, Q1 | E10: 2000 | F10: Year 3, Q1 | G10: 🔴 Critical
A11: Egypt (Cairo, Alexandria, Giza) | B11: 110M | C11: $1.84B | D11: Year 3, Q3 | E11: 3000 | F11: Year 3, Q3 | G11: 🔴 Critical
A12: Palestine (Ramallah, Hebron) | B12: 5.5M | C12: $15–25M | D12: Year 3, Q4 | E12: 300 | F12: ⚠️ Low | G12: 🟡 High
F13: Year 4, Q1
A14: Syria (Damascus, Aleppo) | B14: 23M | C14: $200M (post-stabilization) | D14: Year 5+ | E14: 500 | F14: ❌ Very Low — monitor reconstruction progress | G14: 🔵 Long-term
A15: Syria (Damascus, Aleppo) | B15: 23M | C15: $200M (post-stab.) | D15: Year 5+ | E15: 500 | F15: ❌ Very Low | G15: 🔵 Monitor
A16: Libya & Sudan | B16: 55M | C16: $300M (combined) | D16: Year 5+ | E16: 400 | F16: ❌ Very Low | G16: 🔵 Monitor
A18: TOTAL ADDRESSABLE MARKET
A20: Strategic Logic: GCC markets (UAE, Saudi, Qatar) have higher wages — commission models are tolerable. Our sweet spot is the non-GCC Arab world:
A21: low wages, cash-heavy economies, high unemployment, and millions of drivers for whom keeping 100% of fares is a lifeline.
A23: DETAILED PILOT PROJECTION: IRAQ
A24: Largest non-GCC Arab market — 44M population, massive informal transport sector, JV model with local Iraqi partner
A26: MARKET PROFILE | C26: COMPETITIVE LANDSCAPE
A27: Population | B27: 44 million | C27: Dominant Apps | D27: Careem, Lezzoo, Baly
A28: GDP Per Capita | B28: ~$5,500 | C28: Commission Rate | D28: 25–30%
A29: Ride-Hailing Market | B29: $120M+ est. | C29: Driver Pain Point | D29: High commission, low wages
A30: Currency | B30: Iraqi Dinar (IQD) | C30: Digital Payments | D30: ~15% (cash dominant)
A31: Avg Driver Daily Earnings | B31: ~$15–25/day | C31: Regulatory | D31: Evolving, city-level permits
A32: Key Cities | B32: Baghdad, Erbil, Basra | C32: Wasel Advantage | D32: 0% commission = game changer
A33: Payment Infrastructure | B33: Cash 85%, Digital 15% | C33: Go/No-Go Criteria | D33: 600+ signups in 30 days (JV partner network)
A36: IRAQ PILOT — 3-YEAR QUARTERLY PROJECTION (USD)
B37: Q1 (Launch) | C37: Q2 | D37: Q3 | E37: Q4 | F37: Year 1 Total | G37: Year 2 Total
A38: DRIVER METRICS
A39: New Driver Signups | B39: 600 | C39: 900 | D39: 1200 | E39: 1400 | F39: 4100 | G39: 6000
A40: Churn (quarterly) | B40: -60 | C40: -120 | D40: -190 | E40: -280 | F40: -650 | G40: -1100
A41: Active Drivers (end of Q) | B41: 540 | C41: 1320 | D41: 2330 | E41: 3450 | F41: 3450 | G41: 8350
A43: REVENUE ($)
A44: Subscription Revenue | B44: 32400 | C44: 95040 | D44: 181650 | E44: 276000 | F44: 585090 | G44: 1002000
A45: Ancillary Revenue (ads, data) | B45: 0 | C45: 3000 | D45: 8000 | E45: 15000 | F45: 26000 | G45: 65000
A46: Total Revenue | B46: 32400 | C46: 98040 | D46: 189650 | E46: 291000 | F46: 611090 | G46: 1067000
A48: COSTS ($)
A49: Pre-Launch & Setup (JV: 50/50 split) | B49: -60000 | C49: 0 | D49: 0 | E49: 0 | F49: -60000 | G49: 0
A50: Operations & Staff (local team) | B50: -18000 | C50: -22000 | D50: -28000 | E50: -35000 | F50: -103000 | G50: -170000
A51: Marketing & Driver Acquisition | B51: -35000 | C51: -30000 | D51: -28000 | E51: -25000 | F51: -118000 | G51: -85000
A52: Tech & Platform (local adapt.) | B52: -10000 | C52: -8000 | D52: -7000 | E52: -7000 | F52: -32000 | G52: -25000
A53: Total Costs | B53: =SUM(B49:B52) -> -123000 | C53: =SUM(C49:C52) -> -60000 | D53: =SUM(D49:D52) -> -63000 | E53: =SUM(E49:E52) -> -67000 | F53: =SUM(B53:E53) -> -313000 | G53: =SUM(G49:G52) -> -280000
B54: =B46+B53 -> -90600 | C54: =C46+C53 -> 38040 | D54: =D46+D53 -> 126650 | E54: =E46+E53 -> 224000 | F54: =F46+F53 -> 298090 | G54: =G46+G53 -> 787000
A55: NET INCOME | B55: =B54 -> -90600 | C55: =B55+C54 -> -52560 | D55: =C55+D54 -> 74090 | E55: =D55+E54 -> 298090 | F55: =D55+E54 -> 298090 | G55: =E55+G54 -> 1085090
A56: Cumulative P&L | B56: =B55 -> -90600 | C56: =B56+C55 -> -143160 | D56: =C56+D55 -> -69070 | E56: =D56+E55 -> 229020 | F56: =E56 -> 229020 | G56: =E56+G55 -> 1314110 | H56: I
A58: KEY METRICS
A59: ARPU (avg rev per driver/qtr) | B59: =IF(B41>0,B46/B41,0) -> 60 | C59: =IF(C41>0,C46/C41,0) -> 74.272727 | D59: =IF(D41>0,D46/D41,0) -> 81.39485 | E59: =IF(E41>0,E46/E41,0) -> 84.347826
A60: Net Margin (%) | B60: =IF(B46>0,B55/B46,0) -> -2.7962963 | C60: =IF(C46>0,C55/C46,0) -> -0.53610771 | D60: =IF(D46>0,D55/D46,0) -> 0.39066702 | E60: =IF(E46>0,E55/E46,0) -> 1.0243643 | F60: =IF(F46>0,F55/F46,0) -> 0.48780049 | G60: =IF(G46>0,G55/G46,0) -> 1.0169541
A63: DETAILED PILOT PROJECTION: EGYPT
A64: Largest Arab market by population — 110M people, $1.84B ride-hailing market, massive Uber/Careem driver frustration
A65: MARKET PROFILE | C65: COMPETITIVE LANDSCAPE
A66: Population | B66: 110 million | C66: Dominant Apps | D66: Uber, Careem, Swvl, inDrive
A67: GDP Per Capita | B67: ~$3,800 | C67: Commission Rate | D67: 25–30%
A68: Ride-Hailing Market | B68: $1.84B | C68: Driver Pain Point | D68: EGP devaluation + high fees
A69: Currency | B69: Egyptian Pound (EGP) | C69: Digital Payments | D69: ~25% (growing fast)
A70: Avg Driver Daily Earnings | B70: ~$10–18/day | C70: Regulatory | D70: TRA licensing required
A71: Key Cities | B71: Cairo, Alexandria, Giza | C71: Wasel Advantage | D71: 0% commission in low-wage market
A72: Payment Infrastructure | B72: 600 | C72: 900 | D72: 1200 | E72: 1500 | F72: 4200 | G72: 6000
A73: Est. Subscription Price | B73: -60 | C73: -130 | D73: -210 | E73: -300 | F73: -700 | G73: -1200
B74: 540 | C74: 1310 | D74: 2300 | E74: 3500 | F74: 3500 | G74: 8300
A75: EGYPT PILOT — 3-YEAR QUARTERLY PROJECTION (USD)
B76: Q1 (Launch) | C76: Q2 | D76: Q3 | E76: Q4 | F76: Year 1 Total | G76: Year 2 Total
A77: DRIVER METRICS
A78: New Driver Signups | B78: 24300 | C78: 70650 | D78: 145200 | E78: 252000 | F78: 492150 | G78: 896400
A79: Churn (quarterly) | B79: 0 | C79: 2000 | D79: 6000 | E79: 12000 | F79: 20000 | G79: 60000
A80: Active Drivers (end of Q) | B80: 24300 | C80: 72650 | D80: 151200 | E80: 264000 | F80: 512150 | G80: 956400
A82: REVENUE ($)
A83: Subscription Revenue | B83: -120000 | C83: 0 | D83: 0 | E83: 0 | F83: -120000 | G83: 0
A84: Ancillary Revenue | B84: -30000 | C84: -36000 | D84: -42000 | E84: -50000 | F84: -158000 | G84: -240000
A85: Total Revenue | B85: -45000 | C85: -40000 | D85: -35000 | E85: -32000 | F85: -152000 | G85: -120000
B86: -18000 | C86: -14000 | D86: -11000 | E86: -10000 | F86: -53000 | G86: -40000
A87: COSTS ($)
A88: Pre-Launch & Setup | B88: -120000 | C88: 0 | D88: 0 | E88: 0 | F88: -120000 | G88: 0
A89: Operations & Staff | B89: -188700 | C89: -17350 | D89: 63200 | E89: 172000 | F89: 29150 | G89: 556400
A90: Marketing & Acquisition | B90: -188700 | C90: -206050 | D90: -142850 | E90: 29150 | F90: 29150 | G90: 585550
A91: Tech & Platform (Arabic adapt.) | B91: -20000 | C91: -15000 | D91: -12000 | E91: -12000 | F91: =SUM(B91:E91) -> -59000 | G91: -48000
A92: Total Costs | B92: =B88+B89+B90+B91 -> -517400 | C92: =C88+C89+C90+C91 -> -238400 | D92: =D88+D89+D90+D91 -> -91650 | E92: =E88+E89+E90+E91 -> 189150 | F92: =SUM(B92:E92) -> -658300 | G92: =G88+G89+G90+G91 -> 1093950
A94: NET INCOME | B94: =B85+B92 -> -562400 | C94: =C85+C92 -> -278400 | D94: =D85+D92 -> -126650 | E94: =E85+E92 -> 157150 | F94: =F85+F92 -> -810300 | G94: =G85+G92 -> 973950
A95: Cumulative P&L | B95: =B94 -> -562400 | C95: =B95+C94 -> -840800 | D95: =C95+D94 -> -967450 | E95: =D95+E94 -> -810300 | F95: =E95 -> -810300 | G95: =E95+G94 -> 163650
A97: KEY METRICS
A98: ARPU (avg rev per driver/qtr) | B98: =IF(B80>0,B85/B80,0) -> -1.8518519 | C98: =IF(C80>0,C85/C80,0) -> -0.550585 | D98: =IF(D80>0,D85/D80,0) -> -0.23148148 | E98: =IF(E80>0,E85/E80,0) -> -0.12121212
A99: Net Margin (%) | B99: =IF(B85>0,B94/B85,0) -> 0 | C99: =IF(C85>0,C94/C85,0) -> 0 | D99: =IF(D85>0,D94/D85,0) -> 0 | E99: =IF(E85>0,E94/E85,0) -> 0 | F99: =IF(F85>0,F94/F85,0) -> 0 | G99: =IF(G85>0,G94/G85,0) -> 0
A102: CONSOLIDATED EXPANSION INVESTMENT SUMMARY
A103: Capital requirements, team sizing, and profitability timeline by market
A104: Market | B104: Pilot Capital | C104: Team Size | D104: Break-Even | E104: Y1 Net Income | F104: Y2 Net Income | G104: Y2 Drivers
A105: PHASE 1 — JORDAN DOMESTIC
A106: Irbid | B106: $50K | C106: 3 | D106: Month 6 | E106: $18K | F106: $95K | G106: 1200
A107: Zarqa | B107: $40K | C107: 3 | D107: Month 7 | E107: $12K | F107: $72K | G107: 900
A108: Aqaba | B108: $30K | C108: 2 | D108: Month 8 | E108: $8K | F108: $45K | G108: 600
A110: PHASE 2 — REGIONAL
A111: Iraq (Baghdad, Erbil, Basra) | B111: $120K (JV: 50/50) | C111: 8 | D111: Quarter 2 | E111: =F55 -> 298090 | F111: =G55 -> 1085090 | G111: 8350
A112: Egypt (Cairo, Alex., Giza) | B112: $215K | C112: 10 | D112: Month 8 | E112: =F90 -> 29150 | F112: =G90 -> 585550 | G112: 8300
A113: Palestine (Ramallah, Hebron) | B113: $60K | C113: 3 | D113: Month 10 | E113: $5K | F113: $38K | G113: 800
A115: PHASE 3 — EMERGING (CONTINGENT)
A116: Lebanon, Syria, Libya, Sudan | B116: $100–200K each | C116: 5-8 each | D116: 12–18 months | E116: TBD | F116: TBD | G116: TBD
A118: TOTAL EXPANSION INVESTMENT | B118: $705K–$1.0M | C118: 35–50 staff | D118: 6–10 months avg | E118: $152K+ | F118: $1.4M+ | G118: 20,000+
A120: GO / NO-GO DECISION FRAMEWORK
A122: Criteria | B122: ✅ GO Signal | C122: ⚠️ PAUSE Signal | D122: ❌ NO-GO Signal
...

Sheet Future Revenue Streams
A1: WASEL — FUTURE REVENUE STREAMS
A2: Ancillary & expansion revenue beyond core subscription fees | Launch timeline: Year 2–Year 4
A4: REVENUE STREAM OVERVIEW
A5: Revenue Stream | B5: Launch | C5: Revenue Model | D5: Est. Revenue / Mo (Mature) | E5: Est. Annual (Y5) | F5: Margin | G5: Complexity
A6: 1. Fleet Partner Program | B6: Y2-Q1 | C6: JD 150-300/mo per fleet (5+ cars) | D6: 25000 | E6: =D6*12 -> 300000 | F6: 0.85 | G6: Medium
A7: → Fleet dashboard, bulk onboarding, driver management tools
A8: 2. Corporate Accounts (B2B) | B8: Y2-Q2 | C8: JD 500-2,000/mo per corporate | D8: 35000 | E8: =D8*12 -> 420000 | F8: 0.7 | G8: Medium
A9: → Employee ride credits, monthly billing, priority dispatch for corporate partners
A10: 3. Delivery Partnerships | B10: Y2-Q3 | C10: JD 2-3/delivery commission | D10: 40000 | E10: =D10*12 -> 480000 | F10: 0.4 | G10: High
A11: → Partner with restaurants/grocery; drivers opt-in to delivery during off-peak hours
A12: 4. Insurance Brokerage | B12: Y2-Q4 | C12: JD 5-10/driver/mo commission | D12: 20000 | E12: =D12*12 -> 240000 | F12: 0.9 | G12: Low
A13: → Refer drivers to partner insurers for comprehensive coverage; earn referral commission
A14: 5. In-App Advertising | B14: Y3-Q1 | C14: CPM / sponsored placements | D14: 15000 | E14: =D14*12 -> 180000 | F14: 0.95 | G14: Low
A15: → Sponsored ride offers, driver app banner ads, rider destination suggestions
A16: 6. Data Licensing | B16: Y3-Q2 | C16: Annual contracts with logistics cos | D16: 8000 | E16: =D16*12 -> 96000 | F16: 0.95 | G16: Medium
A17: → Anonymized trip patterns, demand heatmaps sold to logistics/urban planning firms
A18: 7. Rider Subscriptions | B18: Y3-Q3 | C18: JD 5-10/mo rider loyalty pass | D18: 30000 | E18: =D18*12 -> 360000 | F18: 0.8 | G18: Medium
A19: → Priority matching, discounted fares, ride history perks for frequent riders
A21: TOTAL ANCILLARY REVENUE POTENTIAL (Y5) | D21: =SUM(D6,D8,D10,D12,D14,D16,D18) -> 173000 | E21: =D21*12 -> 2076000
A22: Ancillary as % of Core Subscription Rev (Y5) | E22: =E21/'Multi-Year Projections'!F21 -> 0.44060464
A24: REVENUE DIVERSIFICATION ROADMAP
A25: Year | B25: Core Sub Revenue | C25: Ancillary Revenue | D25: Total Revenue | E25: Ancillary Mix % | F25: New Streams Launched
A26: Year 1 | B26: ='Multi-Year Projections'!B21 -> 143881.25 | C26: ='Multi-Year Projections'!B22 -> 0 | D26: ='Multi-Year Projections'!B23 -> 143881.25 | E26: =IF(D26=0,0,C26/D26) -> 0 | F26: None (core only)
A27: Year 2 | B27: ='Multi-Year Projections'!C21 -> 816763.5 | C27: ='Multi-Year Projections'!C22 -> 24120 | D27: ='Multi-Year Projections'!C23 -> 840883.5 | E27: =IF(D27=0,0,C27/D27) -> 0.028684116 | F27: Fleet, Corporate, Delivery
A28: Year 3 | B28: ='Multi-Year Projections'!D21 -> 1712220.7 | C28: ='Multi-Year Projections'!D22 -> 118140 | D28: ='Multi-Year Projections'!D23 -> 1830360.7 | E28: =IF(D28=0,0,C28/D28) -> 0.064544654 | F28: Insurance, Ads, Data, Rider Subs
A29: Year 4 | B29: ='Multi-Year Projections'!E21 -> 3034126.5 | C29: ='Multi-Year Projections'!E22 -> 358884 | D29: ='Multi-Year Projections'!E23 -> 3393010.5 | E29: =IF(D29=0,0,C29/D29) -> 0.10577156 | F29: All 7 streams active
A30: Year 5 | B30: ='Multi-Year Projections'!F21 -> 4711707.1 | C30: ='Multi-Year Projections'!F22 -> 841680 | D30: ='Multi-Year Projections'!F23 -> 5553387.1 | E30: =IF(D30=0,0,C30/D30) -> 0.15156156 | F30: All 7 streams mature
A32: STRATEGIC NOTES
A34: ▶ Ancillary revenue reaches JD 2.1M/yr by Y5 (potential) — currently modeled conservatively at JD 662K in Multi-Year Projections.
A35: ▶ Full ancillary potential adds 56% on top of core subscription revenue, transforming Wasel from a single-product to a platform business.
A36: ▶ Highest-margin streams (Advertising 95%, Insurance 90%, Data 95%) should be prioritized for early launch to maximize profitability.
A37: ▶ Fleet Partner and Corporate Accounts create B2B revenue with longer contracts and lower churn — key for investor confidence.
